[
    {
        "id": 5050,
        "name": "Avoid using HANDLE CONDITION",
        "href": "AIP/quality-rules/5050",
        "critical": false,
        "severity": 10,
        "technologyNames": [
            "Cobol"
        ]
    },
    {
        "id": 5052,
        "name": "Avoid using IGNORE CONDITION",
        "href": "AIP/quality-rules/5052",
        "critical": false,
        "severity": 10,
        "technologyNames": [
            "Cobol"
        ]
    },
    {
        "id": 5054,
        "name": "Avoid using HANDLE ABEND",
        "href": "AIP/quality-rules/5054",
        "critical": false,
        "severity": 10,
        "technologyNames": [
            "Cobol"
        ]
    },
    {
        "id": 5092,
        "name": "Include a WHEN OTHER clause when using EVALUATE",
        "href": "AIP/quality-rules/5092",
        "critical": false,
        "severity": 10,
        "technologyNames": [
            "Cobol"
        ]
    },
    {
        "id": 7548,
        "name": "Never use incompatible statements with the CICS environment",
        "href": "AIP/quality-rules/7548",
        "critical": true,
        "severity": 20,
        "technologyNames": [
            "Cobol"
        ]
    },
    {
        "id": 7688,
        "name": "Never truncate data in MOVE statements",
        "href": "AIP/quality-rules/7688",
        "critical": true,
        "severity": 20,
        "technologyNames": [
            "Cobol"
        ]
    },
    {
        "id": 7690,
        "name": "Avoid unchecked return code (SQLCODE) after EXEC SQL query",
        "href": "AIP/quality-rules/7690",
        "critical": true,
        "severity": 20,
        "technologyNames": [
            "Cobol"
        ]
    },
    {
        "id": 7698,
        "name": "Files should be declared with a FILE-STATUS",
        "href": "AIP/quality-rules/7698",
        "critical": false,
        "severity": 10,
        "technologyNames": [
            "Cobol"
        ]
    },
    {
        "id": 7756,
        "name": "Avoid using READ statement without AT END clause or INVALID KEY clause",
        "href": "AIP/quality-rules/7756",
        "critical": false,
        "severity": 10,
        "technologyNames": [
            "Cobol"
        ]
    },
    {
        "id": 8030,
        "name": "Check alphanumeric data before moving it into numeric data",
        "href": "AIP/quality-rules/8030",
        "critical": false,
        "severity": 10,
        "technologyNames": [
            "Cobol"
        ]
    },
    {
        "id": 8034,
        "name": "Working-Storage variables must be initialized before being read",
        "href": "AIP/quality-rules/8034",
        "critical": false,
        "severity": 10,
        "technologyNames": [
            "Cobol"
        ]
    }
]
