{
    "qualityModel": true,
    "transactionsConfiguration": true,
    "name": "com.castsoftware.tibco",
    "href": "AIP/extensions/com.castsoftware.tibco",
    "title": "Technology Extension For TIBCO",
    "description": "This extension provides support of Tibco BW5 and BW6. Additional quality rules have been integrated. This analyzer enables user to compute Automatic Function Points and provides some Quality checks for Tibco application.",
    "versions": {
        "name": "versions",
        "href": "AIP/extensions/com.castsoftware.tibco/versions"
    }
}
