{
    "id": 7760,
    "name": "Avoid triggers, functions and procedures with a very low comment/code ratio",
    "href": "AIP/quality-rules/7760",
    "critical": false,
    "severity": 10,
    "maxWeight": 3,
    "associatedValueName": "Comment/code ratio",
    "description": "Triggers, functions and procedures must have a comment/code ratio (%) greater than the set threshold value (%)\n\nNote,  threshold is a parameter and can be changed at will.",
    "output": "Associated to each Trigger/Function/Procedure with violations, the Quality Rule provides:\n- The comment / code ratio",
    "rationale": "Maintenability of the code is facilitated if there is documentation in the code. This rule will ensure there are enough comments within triggers, functions and procedures. For PL/SQL code the functions and procedures that are declared in packages is also concerned.",
    "remediation": "Enrich triggers, functions and procedures code with comments",
    "total": "Number of SQL procedures, triggers",
    "alternativeName": "Avoid triggers, functions and procedures with a very low comment/code ratio",
    "businessCriteria": [
        {
            "id": 60012,
            "name": "Changeability",
            "href": "AIP/business-criteria/60012"
        },
        {
            "id": 66033,
            "name": "Documentation",
            "href": "AIP/business-criteria/66033"
        },
        {
            "id": 60017,
            "name": "Total Quality Index",
            "href": "AIP/business-criteria/60017"
        },
        {
            "id": 60011,
            "name": "Transferability",
            "href": "AIP/business-criteria/60011"
        }
    ],
    "technicalCriteria": [
        {
            "id": 61028,
            "name": "Documentation - Volume of Comments",
            "href": "AIP/technical-criteria/61028",
            "weight": 3,
            "critical": false
        }
    ],
    "technologies": [
        {
            "id": -10,
            "name": "Forms",
            "href": "AIP/technologies/-10"
        },
        {
            "id": 140998,
            "name": "Microsoft T-SQL",
            "href": "AIP/technologies/140998"
        },
        {
            "id": 139287,
            "name": "PL/SQL",
            "href": "AIP/technologies/139287"
        },
        {
            "id": 1101000,
            "name": "SQL",
            "href": "AIP/technologies/1101000"
        },
        {
            "id": -13,
            "name": "SQL Server",
            "href": "AIP/technologies/-13"
        },
        {
            "id": 141001,
            "name": "Sybase T-SQL",
            "href": "AIP/technologies/141001"
        }
    ],
    "qualityStandards": [
        
    ],
    "parameters": [
        {
            "name": "Minimum % Comment / Code Ratio",
            "description": "Minimum % Comment / Code Ratio",
            "technologies": [
                {
                    "id": 140998,
                    "name": "Microsoft T-SQL",
                    "href": "AIP/technologies/140998",
                    "values": [
                        5
                    ]
                },
                {
                    "id": 139287,
                    "name": "PL/SQL",
                    "href": "AIP/technologies/139287",
                    "values": [
                        5
                    ]
                },
                {
                    "id": 1101000,
                    "name": "SQL",
                    "href": "AIP/technologies/1101000",
                    "values": [
                        5
                    ]
                },
                {
                    "id": -13,
                    "name": "SQL Server",
                    "href": "AIP/technologies/-13",
                    "values": [
                        5
                    ]
                },
                {
                    "id": 141001,
                    "name": "Sybase T-SQL",
                    "href": "AIP/technologies/141001",
                    "values": [
                        5
                    ]
                }
            ]
        }
    ],
    "thresholds": [
        50.0,
        90.0,
        95.0,
        99.0
    ]
}
