{
    "id": 8030,
    "type": "quality-rule",
    "name": "Check alphanumeric data before moving it into numeric data",
    "href": "AIP/quality-rules/8030",
    "critical": false,
    "maxWeight": 9,
    "associatedValueName": "Number of violation patterns",
    "description": "This rule searches for Cobol programs containing assignments from an alphanumeric variable to a numeric variable where the content of the source data is not previously tested.",
    "output": "Associated to each COBOL Program with violations, the Quality Rule provides:\n- The number of violation patterns\n- Bookmarks for violation patterns found in source code:\n    - MOVE statement from an alphanumeric variable to a numeric variable not enclosed in a test IS NUMERIC\n    - Declaration of the alphanumeric variable\n    - Declaration of the numeric variable",
    "rationale": "In a MOVE statement using a numeric target data (ex: PIC S9(5) COMP-3) and an alphanumeric source data (ex: PIC X(5)), if the source data contains a value that is not numeric (alphabetic, LOW-VALUE, HIGH-VALUE...) and is used in arithmetic operations, then an abend S0C7 will occur. It is important to control the value that will be moved in the numeric variable.",
    "remediation": "For MOVE statement where the target is numeric and the source is alphanumeric, check the type of the value in the source data with an IF NUMERIC condition.",
    "remediationSample": "01 FILE-REC.\n    05 SRC-DATA PIC X(5).\n...\n01 TGT-DATA PIC S9(5) COMP-3.\n...\nREAD MY-FILE INTO FILE-REC.\nIF SRC-DATA IS NUMERIC\n    MOVE SRC-DATA TO TGT-DATA\nELSE\n    DISPLAY \"INVALID VALUE: \" SRC-DATA\nEND-IF",
    "sample": "01 FILE-REC.\n    05 SRC-DATA PIC X(5).\n...\n01 TGT-DATA PIC S9(5) COMP-3.\n...\nREAD MY-FILE INTO FILE-REC.\nMOVE SRC-DATA TO TGT-DATA.",
    "total": "Number of Cobol Programs",
    "businessCriteria": [
        {
            "id": 20140522,
            "name": "Green Stuff",
            "href": "AIP/business-criteria/20140522"
        },
        {
            "id": 66031,
            "name": "Programming Practices",
            "href": "AIP/business-criteria/66031"
        },
        {
            "id": 60013,
            "name": "Robustness",
            "href": "AIP/business-criteria/60013"
        },
        {
            "id": 60016,
            "name": "Security",
            "href": "AIP/business-criteria/60016"
        }
    ],
    "technicalCriteria": [
        {
            "id": 61014,
            "name": "Programming Practices - Error and Exception Handling",
            "weight": 9,
            "critical": false
        }
    ],
    "technologies": [
        {
            "id": -4,
            "name": "Cobol",
            "href": "AIP/technologies/-4"
        }
    ],
    "qualityStandards": [
        
    ]
}
