[
    {
        "name": "1.0.0",
        "href": "AIP/extensions/com.castsoftware.dmtjeegradlediscoverer/versions/1.0.0",
        "metaModelCRC": 0,
        "transactionsConfigurationCRC": null
    },
    {
        "name": "1.0.0-alpha2",
        "href": "AIP/extensions/com.castsoftware.dmtjeegradlediscoverer/versions/1.0.0-alpha2",
        "metaModelCRC": 0,
        "transactionsConfigurationCRC": null
    },
    {
        "name": "1.0.0-alpha1",
        "href": "AIP/extensions/com.castsoftware.dmtjeegradlediscoverer/versions/1.0.0-alpha1",
        "metaModelCRC": 0,
        "transactionsConfigurationCRC": null
    }
]
