[
    {
        "name": "1.0.5",
        "href": "AIP/extensions/com.castsoftware.businessobject/versions/1.0.5",
        "metaModelCRC": 2491964881,
        "rulesCRC": 0,
        "transactionsConfigurationCRC": 1000671812
    },
    {
        "name": "1.0.4",
        "href": "AIP/extensions/com.castsoftware.businessobject/versions/1.0.4",
        "metaModelCRC": 2491964881,
        "rulesCRC": 0,
        "transactionsConfigurationCRC": 1000671812
    },
    {
        "name": "1.0.3",
        "href": "AIP/extensions/com.castsoftware.businessobject/versions/1.0.3",
        "metaModelCRC": 2491964881,
        "rulesCRC": 0,
        "transactionsConfigurationCRC": 2122673973
    },
    {
        "name": "1.0.2",
        "href": "AIP/extensions/com.castsoftware.businessobject/versions/1.0.2",
        "metaModelCRC": 2491964881,
        "rulesCRC": 0,
        "transactionsConfigurationCRC": 4047871659
    },
    {
        "name": "1.0.1-funcrel",
        "href": "AIP/extensions/com.castsoftware.businessobject/versions/1.0.1-funcrel",
        "metaModelCRC": 1192818788,
        "rulesCRC": 0,
        "transactionsConfigurationCRC": 4047871659
    },
    {
        "name": "1.0.0-funcrel",
        "href": "AIP/extensions/com.castsoftware.businessobject/versions/1.0.0-funcrel",
        "metaModelCRC": 0,
        "rulesCRC": 0,
        "transactionsConfigurationCRC": 4047871659
    },
    {
        "name": "1.0.0-beta1",
        "href": "AIP/extensions/com.castsoftware.businessobject/versions/1.0.0-beta1",
        "metaModelCRC": 0,
        "rulesCRC": 0,
        "transactionsConfigurationCRC": null
    }
]
