{
    "extension": {
        "name": "com.castsoftware.php",
        "href": "AIP/extensions/com.castsoftware.php"
    },
    "name": "2.0.0-funcrel",
    "href": "AIP/extensions/com.castsoftware.php/versions/2.0.0-funcrel",
    "publishedTime": "2018-06-29T10:54:55.004826+00:00",
    "qualityModel": true,
    "transactionsConfiguration": true,
    "qualityRules": {
        "name": "Quality Rules in numeric ID order",
        "href": "AIP/extensions/com.castsoftware.php/versions/2.0.0-funcrel/quality-rules"
    }
}
