[
    {
        "name": "2.2.0-funcrel",
        "href": "AIP/extensions/com.castsoftware.jquery/versions/2.2.0-funcrel",
        "metaModelCRC": 1409989270,
        "rulesCRC": 1360831812,
        "transactionsConfigurationCRC": 3857231035
    },
    {
        "name": "2.1.2-funcrel",
        "href": "AIP/extensions/com.castsoftware.jquery/versions/2.1.2-funcrel",
        "metaModelCRC": 1409989270,
        "rulesCRC": 1339141426,
        "transactionsConfigurationCRC": 3857231035
    },
    {
        "name": "2.1.1-funcrel",
        "href": "AIP/extensions/com.castsoftware.jquery/versions/2.1.1-funcrel",
        "metaModelCRC": 1409989270,
        "rulesCRC": 1339141426,
        "transactionsConfigurationCRC": 3857231035
    },
    {
        "name": "2.1.0-funcrel",
        "href": "AIP/extensions/com.castsoftware.jquery/versions/2.1.0-funcrel",
        "metaModelCRC": 1409989270,
        "rulesCRC": 1339141426,
        "transactionsConfigurationCRC": 3857231035
    },
    {
        "name": "2.1.0-beta3",
        "href": "AIP/extensions/com.castsoftware.jquery/versions/2.1.0-beta3",
        "metaModelCRC": 1409989270,
        "rulesCRC": 1339141426,
        "transactionsConfigurationCRC": 3857231035
    },
    {
        "name": "2.1.0-beta2",
        "href": "AIP/extensions/com.castsoftware.jquery/versions/2.1.0-beta2",
        "metaModelCRC": 1409989270,
        "rulesCRC": 1339141426,
        "transactionsConfigurationCRC": 3857231035
    },
    {
        "name": "2.1.0-beta1",
        "href": "AIP/extensions/com.castsoftware.jquery/versions/2.1.0-beta1",
        "metaModelCRC": 1409989270,
        "rulesCRC": 1339141426,
        "transactionsConfigurationCRC": 3857231035
    },
    {
        "name": "2.0.0-funcrel",
        "href": "AIP/extensions/com.castsoftware.jquery/versions/2.0.0-funcrel",
        "metaModelCRC": 1409989270,
        "rulesCRC": 2942274741,
        "transactionsConfigurationCRC": 3857231035
    },
    {
        "name": "2.0.0-beta1",
        "href": "AIP/extensions/com.castsoftware.jquery/versions/2.0.0-beta1",
        "metaModelCRC": 1409989270,
        "rulesCRC": 1929737468,
        "transactionsConfigurationCRC": 3857231035
    },
    {
        "name": "1.7.2-funcrel",
        "href": "AIP/extensions/com.castsoftware.jquery/versions/1.7.2-funcrel",
        "metaModelCRC": 1409989270,
        "rulesCRC": 4107142794,
        "transactionsConfigurationCRC": 3857231035
    },
    {
        "name": "1.7.1-funcrel",
        "href": "AIP/extensions/com.castsoftware.jquery/versions/1.7.1-funcrel",
        "metaModelCRC": 1409989270,
        "rulesCRC": 4107142794,
        "transactionsConfigurationCRC": 1395943227
    },
    {
        "name": "1.7.0-funcrel",
        "href": "AIP/extensions/com.castsoftware.jquery/versions/1.7.0-funcrel",
        "metaModelCRC": 1409989270,
        "rulesCRC": 173383755,
        "transactionsConfigurationCRC": 1395943227
    },
    {
        "name": "1.7.0-beta1",
        "href": "AIP/extensions/com.castsoftware.jquery/versions/1.7.0-beta1",
        "metaModelCRC": 1409989270,
        "rulesCRC": 173383755,
        "transactionsConfigurationCRC": 1395943227
    },
    {
        "name": "1.6.0",
        "href": "AIP/extensions/com.castsoftware.jquery/versions/1.6.0",
        "metaModelCRC": 1409989270,
        "rulesCRC": 173383755,
        "transactionsConfigurationCRC": 1395943227
    },
    {
        "name": "1.6.0-funcrel",
        "href": "AIP/extensions/com.castsoftware.jquery/versions/1.6.0-funcrel",
        "metaModelCRC": 1409989270,
        "rulesCRC": 173383755,
        "transactionsConfigurationCRC": 1395943227
    },
    {
        "name": "1.6.0-alpha1",
        "href": "AIP/extensions/com.castsoftware.jquery/versions/1.6.0-alpha1",
        "metaModelCRC": 1409989270,
        "rulesCRC": 173383755,
        "transactionsConfigurationCRC": 1395943227
    },
    {
        "name": "1.5.0-funcrel",
        "href": "AIP/extensions/com.castsoftware.jquery/versions/1.5.0-funcrel",
        "metaModelCRC": 1409989270,
        "rulesCRC": 173383755,
        "transactionsConfigurationCRC": 1395943227
    },
    {
        "name": "1.5.0-beta4",
        "href": "AIP/extensions/com.castsoftware.jquery/versions/1.5.0-beta4",
        "metaModelCRC": 1409989270,
        "rulesCRC": 173383755,
        "transactionsConfigurationCRC": 1395943227
    },
    {
        "name": "1.5.0-beta3",
        "href": "AIP/extensions/com.castsoftware.jquery/versions/1.5.0-beta3",
        "metaModelCRC": 1409989270,
        "rulesCRC": 173383755,
        "transactionsConfigurationCRC": 1395943227
    },
    {
        "name": "1.5.0-beta2",
        "href": "AIP/extensions/com.castsoftware.jquery/versions/1.5.0-beta2",
        "metaModelCRC": 1409989270,
        "rulesCRC": 173383755,
        "transactionsConfigurationCRC": null
    },
    {
        "name": "1.5.0-beta1",
        "href": "AIP/extensions/com.castsoftware.jquery/versions/1.5.0-beta1",
        "metaModelCRC": 1409989270,
        "rulesCRC": 173383755,
        "transactionsConfigurationCRC": null
    },
    {
        "name": "1.5.0-alpha1",
        "href": "AIP/extensions/com.castsoftware.jquery/versions/1.5.0-alpha1",
        "metaModelCRC": 1409989270,
        "rulesCRC": 173383755,
        "transactionsConfigurationCRC": null
    },
    {
        "name": "1.4.0-funcrel",
        "href": "AIP/extensions/com.castsoftware.jquery/versions/1.4.0-funcrel",
        "metaModelCRC": 1409989270,
        "rulesCRC": 173383755,
        "transactionsConfigurationCRC": null
    },
    {
        "name": "1.3.0-funcrel",
        "href": "AIP/extensions/com.castsoftware.jquery/versions/1.3.0-funcrel",
        "metaModelCRC": 1409989270,
        "rulesCRC": 173383755,
        "transactionsConfigurationCRC": null
    },
    {
        "name": "1.2.0-funcrel",
        "href": "AIP/extensions/com.castsoftware.jquery/versions/1.2.0-funcrel",
        "metaModelCRC": 1409989270,
        "rulesCRC": 173383755,
        "transactionsConfigurationCRC": null
    },
    {
        "name": "1.2.0-beta4",
        "href": "AIP/extensions/com.castsoftware.jquery/versions/1.2.0-beta4",
        "metaModelCRC": 1409989270,
        "rulesCRC": 173383755,
        "transactionsConfigurationCRC": null
    },
    {
        "name": "1.2.0-beta3",
        "href": "AIP/extensions/com.castsoftware.jquery/versions/1.2.0-beta3",
        "metaModelCRC": 1409989270,
        "rulesCRC": 173383755,
        "transactionsConfigurationCRC": null
    },
    {
        "name": "1.2.0-beta1",
        "href": "AIP/extensions/com.castsoftware.jquery/versions/1.2.0-beta1",
        "metaModelCRC": 1409989270,
        "rulesCRC": 173383755,
        "transactionsConfigurationCRC": null
    },
    {
        "name": "1.1.0-funcrel",
        "href": "AIP/extensions/com.castsoftware.jquery/versions/1.1.0-funcrel",
        "metaModelCRC": 1409989270,
        "rulesCRC": 173383755,
        "transactionsConfigurationCRC": null
    },
    {
        "name": "1.1.0-beta1",
        "href": "AIP/extensions/com.castsoftware.jquery/versions/1.1.0-beta1",
        "metaModelCRC": 1409989270,
        "rulesCRC": 173383755,
        "transactionsConfigurationCRC": null
    },
    {
        "name": "1.1.0-alpha6",
        "href": "AIP/extensions/com.castsoftware.jquery/versions/1.1.0-alpha6",
        "metaModelCRC": 1409989270,
        "rulesCRC": 173383755,
        "transactionsConfigurationCRC": null
    },
    {
        "name": "1.1.0-alpha4",
        "href": "AIP/extensions/com.castsoftware.jquery/versions/1.1.0-alpha4",
        "metaModelCRC": 1409989270,
        "rulesCRC": 3690357209,
        "transactionsConfigurationCRC": null
    },
    {
        "name": "1.1.0-alpha3",
        "href": "AIP/extensions/com.castsoftware.jquery/versions/1.1.0-alpha3",
        "metaModelCRC": 1409989270,
        "rulesCRC": 3690357209,
        "transactionsConfigurationCRC": null
    },
    {
        "name": "1.1.0-alpha2",
        "href": "AIP/extensions/com.castsoftware.jquery/versions/1.1.0-alpha2",
        "metaModelCRC": 1409989270,
        "rulesCRC": 3690357209,
        "transactionsConfigurationCRC": null
    },
    {
        "name": "1.1.0-alpha1",
        "href": "AIP/extensions/com.castsoftware.jquery/versions/1.1.0-alpha1",
        "metaModelCRC": 1409989270,
        "rulesCRC": 3474875713,
        "transactionsConfigurationCRC": null
    },
    {
        "name": "1.0.0-funcrel",
        "href": "AIP/extensions/com.castsoftware.jquery/versions/1.0.0-funcrel",
        "metaModelCRC": 1409989270,
        "rulesCRC": 1114025186,
        "transactionsConfigurationCRC": null
    }
]
