[
    {
        "id": 566,
        "name": "Avoid large Classes - too many Methods (C++)",
        "href": "AIP/quality-rules/566",
        "status": null,
        "critical": false,
        "technologyNames": [
            "C++"
        ]
    },
    {
        "id": 568,
        "name": "Avoid large Classes - too many Data Members (C++)",
        "href": "AIP/quality-rules/568",
        "status": null,
        "critical": false,
        "technologyNames": [
            "C++"
        ]
    },
    {
        "id": 570,
        "name": "Avoid large Interfaces - too many Methods (C++)",
        "href": "AIP/quality-rules/570",
        "status": null,
        "critical": false,
        "technologyNames": [
            "C++"
        ]
    },
    {
        "id": 576,
        "name": "Avoid large Classes - too many Constructors (C++)",
        "href": "AIP/quality-rules/576",
        "status": null,
        "critical": false,
        "technologyNames": [
            "C++"
        ]
    },
    {
        "id": 578,
        "name": "Avoid Classes with multiple inheritance",
        "href": "AIP/quality-rules/578",
        "status": null,
        "critical": false,
        "technologyNames": [
            "C++"
        ]
    },
    {
        "id": 580,
        "name": "Avoid using Structures",
        "href": "AIP/quality-rules/580",
        "status": null,
        "critical": false,
        "technologyNames": [
            "C++"
        ]
    },
    {
        "id": 584,
        "name": "Avoid Classes with at least one virtual Function and without a virtual Destructor",
        "href": "AIP/quality-rules/584",
        "status": null,
        "critical": false,
        "technologyNames": [
            "C++"
        ]
    },
    {
        "id": 588,
        "name": "Avoid using Global Variables (C++)",
        "href": "AIP/quality-rules/588",
        "status": null,
        "critical": false,
        "technologyNames": [
            "C++"
        ]
    },
    {
        "id": 590,
        "name": "Avoid using global objects in Constructors and Destructors",
        "href": "AIP/quality-rules/590",
        "status": null,
        "critical": false,
        "technologyNames": [
            "C++"
        ]
    },
    {
        "id": 620,
        "name": "Avoid base Classes without virtual Destructors",
        "href": "AIP/quality-rules/620",
        "status": null,
        "critical": false,
        "technologyNames": [
            "C++"
        ]
    },
    {
        "id": 628,
        "name": "Avoid invocation of virtual Methods of the declared Class in a Constructor or Destructor",
        "href": "AIP/quality-rules/628",
        "status": null,
        "critical": true,
        "technologyNames": [
            "C++"
        ]
    },
    {
        "id": 630,
        "name": "Avoid data members that are not private",
        "href": "AIP/quality-rules/630",
        "status": null,
        "critical": false,
        "technologyNames": [
            "C++"
        ]
    },
    {
        "id": 634,
        "name": "Avoid using VARIANT Structures",
        "href": "AIP/quality-rules/634",
        "status": null,
        "critical": false,
        "technologyNames": [
            "C++"
        ]
    },
    {
        "id": 678,
        "name": "Never throw an exception from a Destructor",
        "href": "AIP/quality-rules/678",
        "status": null,
        "critical": true,
        "technologyNames": [
            "C++"
        ]
    },
    {
        "id": 1058,
        "name": "Avoid large Files - too many Lines of Code",
        "href": "AIP/quality-rules/1058",
        "status": null,
        "critical": false,
        "technologyNames": [
            "C",
            "C++"
        ]
    },
    {
        "id": 1060,
        "name": "Avoid large Macros - too many Lines of Code",
        "href": "AIP/quality-rules/1060",
        "status": null,
        "critical": false,
        "technologyNames": [
            "C",
            "C++"
        ]
    },
    {
        "id": 1072,
        "name": "Avoid using memory management Functions (free/malloc/realloc)",
        "href": "AIP/quality-rules/1072",
        "status": null,
        "critical": false,
        "technologyNames": [
            "C",
            "C++"
        ]
    },
    {
        "id": 1074,
        "name": "Avoid using signals management Functions",
        "href": "AIP/quality-rules/1074",
        "status": null,
        "critical": false,
        "technologyNames": [
            "C",
            "C++"
        ]
    },
    {
        "id": 2232,
        "name": "Pages should use error handling page",
        "href": "AIP/quality-rules/2232",
        "status": null,
        "critical": false,
        "technologyNames": [
            "JEE"
        ]
    },
    {
        "id": 2242,
        "name": "Avoid direct definition of JavaScript Functions in a Web page (JEE)",
        "href": "AIP/quality-rules/2242",
        "status": null,
        "critical": false,
        "technologyNames": [
            "JEE"
        ]
    },
    {
        "id": 2254,
        "name": "Avoid large Page files (JEE)",
        "href": "AIP/quality-rules/2254",
        "status": null,
        "critical": false,
        "technologyNames": [
            "JEE"
        ]
    },
    {
        "id": 2278,
        "name": "Check the use of \"foreach\" custom tag library",
        "href": "AIP/quality-rules/2278",
        "status": null,
        "critical": false,
        "technologyNames": [
            "JEE"
        ]
    },
    {
        "id": 2280,
        "name": "Avoid using Document.all collection",
        "href": "AIP/quality-rules/2280",
        "status": null,
        "critical": false,
        "technologyNames": [
            "JEE"
        ]
    },
    {
        "id": 2282,
        "name": "Avoid large Include Files",
        "href": "AIP/quality-rules/2282",
        "status": null,
        "critical": false,
        "technologyNames": [
            "JEE"
        ]
    },
    {
        "id": 2284,
        "name": "Avoid large JSP Pages - too many Scriptlets",
        "href": "AIP/quality-rules/2284",
        "status": null,
        "critical": false,
        "technologyNames": [
            "JEE"
        ]
    },
    {
        "id": 3148,
        "name": "An include file must contain at most one Class definition",
        "href": "AIP/quality-rules/3148",
        "status": null,
        "critical": false,
        "technologyNames": [
            "C++"
        ]
    },
    {
        "id": 4554,
        "name": "Avoid large Classes - too many Methods (JEE)",
        "href": "AIP/quality-rules/4554",
        "status": null,
        "critical": false,
        "technologyNames": [
            "JEE"
        ]
    },
    {
        "id": 4556,
        "name": "Avoid large Classes - too many Constructors (JEE)",
        "href": "AIP/quality-rules/4556",
        "status": null,
        "critical": false,
        "technologyNames": [
            "JEE"
        ]
    },
    {
        "id": 4558,
        "name": "Avoid large Classes - too many Fields",
        "href": "AIP/quality-rules/4558",
        "status": null,
        "critical": false,
        "technologyNames": [
            "JEE"
        ]
    },
    {
        "id": 4560,
        "name": "Avoid large Interfaces - too many Methods (JEE)",
        "href": "AIP/quality-rules/4560",
        "status": null,
        "critical": false,
        "technologyNames": [
            "JEE"
        ]
    },
    {
        "id": 4566,
        "name": "Avoid declaring Instance Variables without defined access type",
        "href": "AIP/quality-rules/4566",
        "status": null,
        "critical": false,
        "technologyNames": [
            "JEE"
        ]
    },
    {
        "id": 4568,
        "name": "Avoid declaring Public Instance Variables",
        "href": "AIP/quality-rules/4568",
        "status": null,
        "critical": true,
        "technologyNames": [
            "JEE"
        ]
    },
    {
        "id": 4570,
        "name": "Avoid declaring Non Final Class Variables with Public or Package access type",
        "href": "AIP/quality-rules/4570",
        "status": null,
        "critical": false,
        "technologyNames": [
            "JEE"
        ]
    },
    {
        "id": 4572,
        "name": "Avoid declaring Final Instance Variables that are not dynamically initialized",
        "href": "AIP/quality-rules/4572",
        "status": null,
        "critical": false,
        "technologyNames": [
            "JEE"
        ]
    },
    {
        "id": 4576,
        "name": "Provide accessors to Private Fields",
        "href": "AIP/quality-rules/4576",
        "status": null,
        "critical": false,
        "technologyNames": [
            "JEE"
        ]
    },
    {
        "id": 4578,
        "name": "Good use of Interfaces with collections as Method return types",
        "href": "AIP/quality-rules/4578",
        "status": null,
        "critical": false,
        "technologyNames": [
            "JEE"
        ]
    },
    {
        "id": 4580,
        "name": "Good use of Interfaces when instantiating a collection",
        "href": "AIP/quality-rules/4580",
        "status": null,
        "critical": false,
        "technologyNames": [
            "JEE"
        ]
    },
    {
        "id": 4592,
        "name": "Avoid hiding static Methods",
        "href": "AIP/quality-rules/4592",
        "status": null,
        "critical": true,
        "technologyNames": [
            "JEE"
        ]
    },
    {
        "id": 4600,
        "name": "Avoid using 'java.System.exit()'",
        "href": "AIP/quality-rules/4600",
        "status": null,
        "critical": false,
        "technologyNames": [
            "JEE"
        ]
    },
    {
        "id": 4602,
        "name": "Avoid using Fields (non static final) from other Classes",
        "href": "AIP/quality-rules/4602",
        "status": null,
        "critical": true,
        "technologyNames": [
            "JEE"
        ]
    },
    {
        "id": 4604,
        "name": "Avoid using 'java.lang.Error'",
        "href": "AIP/quality-rules/4604",
        "status": null,
        "critical": false,
        "technologyNames": [
            "JEE"
        ]
    },
    {
        "id": 4610,
        "name": "Avoid using anonymous Classes",
        "href": "AIP/quality-rules/4610",
        "status": null,
        "critical": false,
        "technologyNames": [
            "JEE"
        ]
    },
    {
        "id": 4614,
        "name": "Proper overriding of 'clone()'",
        "href": "AIP/quality-rules/4614",
        "status": null,
        "critical": true,
        "technologyNames": [
            "JEE"
        ]
    },
    {
        "id": 4616,
        "name": "Proper overriding of 'finalize()'",
        "href": "AIP/quality-rules/4616",
        "status": null,
        "critical": true,
        "technologyNames": [
            "JEE"
        ]
    },
    {
        "id": 4618,
        "name": "Avoid instantiating Boolean",
        "href": "AIP/quality-rules/4618",
        "status": null,
        "critical": false,
        "technologyNames": [
            "JEE"
        ]
    },
    {
        "id": 4652,
        "name": "Avoid direct Class inheritance from java.lang.Throwable",
        "href": "AIP/quality-rules/4652",
        "status": null,
        "critical": false,
        "technologyNames": [
            "JEE"
        ]
    },
    {
        "id": 4656,
        "name": "Avoid declaring throwing an exception and not throwing it",
        "href": "AIP/quality-rules/4656",
        "status": null,
        "critical": false,
        "technologyNames": [
            "JEE"
        ]
    },
    {
        "id": 4694,
        "name": "Avoid using 'System.gc'",
        "href": "AIP/quality-rules/4694",
        "status": null,
        "critical": false,
        "technologyNames": [
            "JEE"
        ]
    },
    {
        "id": 4696,
        "name": "Avoid using 'System.err' and 'System.out' within a try catch block",
        "href": "AIP/quality-rules/4696",
        "status": null,
        "critical": false,
        "technologyNames": [
            "JEE"
        ]
    },
    {
        "id": 4698,
        "name": "Avoid using 'System.err' and 'System.out' outside a try catch block",
        "href": "AIP/quality-rules/4698",
        "status": null,
        "critical": false,
        "technologyNames": [
            "JEE"
        ]
    },
    {
        "id": 4702,
        "name": "Avoid using 'Throwable.printStackTrace()' with no argument",
        "href": "AIP/quality-rules/4702",
        "status": null,
        "critical": false,
        "technologyNames": [
            "JEE"
        ]
    },
    {
        "id": 4704,
        "name": "Avoid using Vector",
        "href": "AIP/quality-rules/4704",
        "status": null,
        "critical": false,
        "technologyNames": [
            "JEE"
        ]
    },
    {
        "id": 4706,
        "name": "Avoid using Hashtable",
        "href": "AIP/quality-rules/4706",
        "status": null,
        "critical": false,
        "technologyNames": [
            "JEE"
        ]
    },
    {
        "id": 4708,
        "name": "Avoid using Dynamic instantiation",
        "href": "AIP/quality-rules/4708",
        "status": null,
        "critical": false,
        "technologyNames": [
            "JEE"
        ]
    },
    {
        "id": 4716,
        "name": "Avoid Classes implementing too many Interfaces (JEE)",
        "href": "AIP/quality-rules/4716",
        "status": null,
        "critical": false,
        "technologyNames": [
            "JEE"
        ]
    },
    {
        "id": 4744,
        "name": "EJB Entity access through their local Interface",
        "href": "AIP/quality-rules/4744",
        "status": null,
        "critical": true,
        "technologyNames": [
            "JEE"
        ]
    },
    {
        "id": 4746,
        "name": "EJB Session access through their local Interface",
        "href": "AIP/quality-rules/4746",
        "status": null,
        "critical": true,
        "technologyNames": [
            "JEE"
        ]
    },
    {
        "id": 7132,
        "name": "Action Mappings should have few forwards",
        "href": "AIP/quality-rules/7132",
        "status": null,
        "critical": false,
        "technologyNames": [
            "JEE"
        ]
    },
    {
        "id": 7136,
        "name": "Each method in an Action Class should have a small complexity",
        "href": "AIP/quality-rules/7136",
        "status": null,
        "critical": false,
        "technologyNames": [
            "JEE"
        ]
    },
    {
        "id": 7150,
        "name": "Favor PreparedStatement or CallableStatement over Statement",
        "href": "AIP/quality-rules/7150",
        "status": null,
        "critical": false,
        "technologyNames": [
            "JEE"
        ]
    },
    {
        "id": 7152,
        "name": "Avoid Fields in Servlet Classes that are not final static",
        "href": "AIP/quality-rules/7152",
        "status": null,
        "critical": true,
        "technologyNames": [
            "JEE"
        ]
    },
    {
        "id": 7154,
        "name": "Avoid Fields in Action Classes that are not final static",
        "href": "AIP/quality-rules/7154",
        "status": null,
        "critical": true,
        "technologyNames": [
            "JEE"
        ]
    },
    {
        "id": 7196,
        "name": "Avoid large number of String concatenation (JEE)",
        "href": "AIP/quality-rules/7196",
        "status": null,
        "critical": false,
        "technologyNames": [
            "JEE"
        ]
    },
    {
        "id": 7200,
        "name": "Avoid String concatenation in loops (JEE)",
        "href": "AIP/quality-rules/7200",
        "status": null,
        "critical": false,
        "technologyNames": [
            "JEE"
        ]
    },
    {
        "id": 7204,
        "name": "Avoid method invocation in a loop termination expression",
        "href": "AIP/quality-rules/7204",
        "status": null,
        "critical": false,
        "technologyNames": [
            "ALL TECHNOLOGIES"
        ]
    },
    {
        "id": 7206,
        "name": "Avoid the use of InstanceOf inside loops",
        "href": "AIP/quality-rules/7206",
        "status": null,
        "critical": false,
        "technologyNames": [
            "JEE"
        ]
    },
    {
        "id": 7210,
        "name": "Avoid instantiations inside loops",
        "href": "AIP/quality-rules/7210",
        "status": null,
        "critical": true,
        "technologyNames": [
            "JEE"
        ]
    },
    {
        "id": 7220,
        "name": "Avoid Unused Imports",
        "href": "AIP/quality-rules/7220",
        "status": null,
        "critical": false,
        "technologyNames": [
            "JEE"
        ]
    },
    {
        "id": 7250,
        "name": "Avoid String initialization with String object (created using the 'new' keyword)",
        "href": "AIP/quality-rules/7250",
        "status": null,
        "critical": false,
        "technologyNames": [
            "JEE"
        ]
    },
    {
        "id": 7252,
        "name": "Call 'super.finalize ()' in the \"finally\" block of 'finalize ()' methods",
        "href": "AIP/quality-rules/7252",
        "status": null,
        "critical": false,
        "technologyNames": [
            "JEE"
        ]
    },
    {
        "id": 7296,
        "name": "Never define static variables in header files",
        "href": "AIP/quality-rules/7296",
        "status": null,
        "critical": true,
        "technologyNames": [
            "C",
            "C++"
        ]
    },
    {
        "id": 7306,
        "name": "Avoid declaring Inner Classes",
        "href": "AIP/quality-rules/7306",
        "status": null,
        "critical": false,
        "technologyNames": [
            "JEE"
        ]
    },
    {
        "id": 7308,
        "name": "Avoid using Inner Classes",
        "href": "AIP/quality-rules/7308",
        "status": null,
        "critical": false,
        "technologyNames": [
            "JEE"
        ]
    },
    {
        "id": 7340,
        "name": "Avoid Classes with Destructor not explicitly virtual whenever one of its base Class has a virtual Destructor",
        "href": "AIP/quality-rules/7340",
        "status": null,
        "critical": false,
        "technologyNames": [
            "C++"
        ]
    },
    {
        "id": 7342,
        "name": "Avoid functions overriding virtual functions without having the 'virtual' keyword",
        "href": "AIP/quality-rules/7342",
        "status": null,
        "critical": false,
        "technologyNames": [
            "C++"
        ]
    },
    {
        "id": 7362,
        "name": "Avoid action mappings validator turned off",
        "href": "AIP/quality-rules/7362",
        "status": null,
        "critical": true,
        "technologyNames": [
            "JEE"
        ]
    },
    {
        "id": 7372,
        "name": "Enable Struts Validator plugin",
        "href": "AIP/quality-rules/7372",
        "status": null,
        "critical": true,
        "technologyNames": [
            "JEE"
        ]
    },
    {
        "id": 7380,
        "name": "Avoid unused validation form",
        "href": "AIP/quality-rules/7380",
        "status": null,
        "critical": false,
        "technologyNames": [
            "JEE"
        ]
    },
    {
        "id": 7382,
        "name": "Avoid Validator field without Form Field",
        "href": "AIP/quality-rules/7382",
        "status": null,
        "critical": false,
        "technologyNames": [
            "JEE"
        ]
    },
    {
        "id": 7388,
        "name": "Avoid artifacts having recursive calls",
        "href": "AIP/quality-rules/7388",
        "status": null,
        "critical": false,
        "technologyNames": [
            "ALL TECHNOLOGIES"
        ]
    },
    {
        "id": 7424,
        "name": "Avoid using SQL queries inside a loop",
        "href": "AIP/quality-rules/7424",
        "status": null,
        "critical": true,
        "technologyNames": [
            "ALL TECHNOLOGIES"
        ]
    },
    {
        "id": 7434,
        "name": "Avoid classes overriding only equals() or only hashCode()",
        "href": "AIP/quality-rules/7434",
        "status": null,
        "critical": true,
        "technologyNames": [
            "JEE"
        ]
    },
    {
        "id": 7440,
        "name": "Suspicious similar method names or signatures in an inheritance tree",
        "href": "AIP/quality-rules/7440",
        "status": null,
        "critical": true,
        "technologyNames": [
            "JEE"
        ]
    },
    {
        "id": 7442,
        "name": "Avoid to use this within Constructor in multi-thread environment",
        "href": "AIP/quality-rules/7442",
        "status": null,
        "critical": true,
        "technologyNames": [
            "JEE"
        ]
    },
    {
        "id": 7446,
        "name": "Avoid double checked locking",
        "href": "AIP/quality-rules/7446",
        "status": null,
        "critical": true,
        "technologyNames": [
            "JEE"
        ]
    },
    {
        "id": 7488,
        "name": "Use lazy fetching for collection",
        "href": "AIP/quality-rules/7488",
        "status": null,
        "critical": true,
        "technologyNames": [
            "JEE"
        ]
    },
    {
        "id": 7502,
        "name": "Never use array to map a collection",
        "href": "AIP/quality-rules/7502",
        "status": null,
        "critical": true,
        "technologyNames": [
            "JEE"
        ]
    },
    {
        "id": 7562,
        "name": "Avoid static Field of type collection",
        "href": "AIP/quality-rules/7562",
        "status": null,
        "critical": false,
        "technologyNames": [
            "JEE"
        ]
    },
    {
        "id": 7636,
        "name": "Use version instead of timestamp",
        "href": "AIP/quality-rules/7636",
        "status": null,
        "critical": false,
        "technologyNames": [
            "JEE"
        ]
    },
    {
        "id": 7638,
        "name": "Avoid using DriverManager",
        "href": "AIP/quality-rules/7638",
        "status": null,
        "critical": false,
        "technologyNames": [
            "JEE"
        ]
    },
    {
        "id": 7640,
        "name": "Avoid catch blocks with assertion",
        "href": "AIP/quality-rules/7640",
        "status": null,
        "critical": false,
        "technologyNames": [
            "JEE"
        ]
    },
    {
        "id": 7648,
        "name": "Avoid calling finalize()",
        "href": "AIP/quality-rules/7648",
        "status": null,
        "critical": false,
        "technologyNames": [
            "JEE"
        ]
    },
    {
        "id": 7652,
        "name": "Avoid throwing an exception in a catch block without chaining it",
        "href": "AIP/quality-rules/7652",
        "status": null,
        "critical": false,
        "technologyNames": [
            "JEE"
        ]
    },
    {
        "id": 7668,
        "name": "Avoid using incorrect XML parsing model",
        "href": "AIP/quality-rules/7668",
        "status": null,
        "critical": false,
        "technologyNames": [
            "JEE"
        ]
    },
    {
        "id": 7720,
        "name": "Avoid too many EJB bean",
        "href": "AIP/quality-rules/7720",
        "status": null,
        "critical": true,
        "technologyNames": [
            "JEE"
        ]
    },
    {
        "id": 7732,
        "name": "Avoid non validated inputs",
        "href": "AIP/quality-rules/7732",
        "status": null,
        "critical": true,
        "technologyNames": [
            "JEE"
        ]
    },
    {
        "id": 7734,
        "name": "Avoid to use Log.debug() without calling Log.isDebugEnabled()",
        "href": "AIP/quality-rules/7734",
        "status": null,
        "critical": false,
        "technologyNames": [
            "JEE"
        ]
    },
    {
        "id": 7740,
        "name": "Avoid cross-site scripting vulnerabilities",
        "href": "AIP/quality-rules/7740",
        "status": null,
        "critical": true,
        "technologyNames": [
            "JEE"
        ]
    },
    {
        "id": 7742,
        "name": "Avoid SQL injection vulnerabilities",
        "href": "AIP/quality-rules/7742",
        "status": null,
        "critical": true,
        "technologyNames": [
            "JEE"
        ]
    },
    {
        "id": 7746,
        "name": "Avoid LDAP injection vulnerabilities",
        "href": "AIP/quality-rules/7746",
        "status": null,
        "critical": true,
        "technologyNames": [
            "JEE"
        ]
    },
    {
        "id": 7748,
        "name": "Avoid OS command injection vulnerabilities",
        "href": "AIP/quality-rules/7748",
        "status": null,
        "critical": true,
        "technologyNames": [
            "JEE"
        ]
    },
    {
        "id": 7750,
        "name": "Avoid XPath injection vulnerabilities",
        "href": "AIP/quality-rules/7750",
        "status": null,
        "critical": true,
        "technologyNames": [
            "JEE"
        ]
    },
    {
        "id": 7752,
        "name": "Avoid file path manipulation vulnerabilities",
        "href": "AIP/quality-rules/7752",
        "status": null,
        "critical": true,
        "technologyNames": [
            "JEE"
        ]
    },
    {
        "id": 7782,
        "name": "Avoid empty finally blocks",
        "href": "AIP/quality-rules/7782",
        "status": null,
        "critical": false,
        "technologyNames": [
            "HTML5",
            "JEE"
        ]
    },
    {
        "id": 7788,
        "name": "Avoid empty catch blocks",
        "href": "AIP/quality-rules/7788",
        "status": null,
        "critical": true,
        "technologyNames": [
            "HTML5",
            "JEE"
        ]
    },
    {
        "id": 7792,
        "name": "Avoid Classes with a High Number Of Children",
        "href": "AIP/quality-rules/7792",
        "status": null,
        "critical": false,
        "technologyNames": [
            "C++",
            "HTML5",
            "JEE"
        ]
    },
    {
        "id": 7794,
        "name": "Avoid Classes with a High Public Data Ratio",
        "href": "AIP/quality-rules/7794",
        "status": null,
        "critical": false,
        "technologyNames": [
            "C++",
            "JEE"
        ]
    },
    {
        "id": 7824,
        "name": "The exception Exception should never been thrown. Always Subclass Exception and throw the subclassed Classes.",
        "href": "AIP/quality-rules/7824",
        "status": null,
        "critical": true,
        "technologyNames": [
            "JEE"
        ]
    },
    {
        "id": 7842,
        "name": "Avoid large Artifacts - too many Lines of Code",
        "href": "AIP/quality-rules/7842",
        "status": null,
        "critical": false,
        "technologyNames": [
            "C",
            "C++",
            "HTML5",
            "JEE",
            "SQLAnalyzer"
        ]
    },
    {
        "id": 7862,
        "name": "Avoid catching an exception of type Exception, RuntimeException, or Throwable",
        "href": "AIP/quality-rules/7862",
        "status": null,
        "critical": false,
        "technologyNames": [
            "JEE"
        ]
    },
    {
        "id": 7910,
        "name": "Never exit a finally block with a return, break, continue, or throw",
        "href": "AIP/quality-rules/7910",
        "status": null,
        "critical": true,
        "technologyNames": [
            "JEE"
        ]
    },
    {
        "id": 7922,
        "name": "Avoid usage of 'std::find_first_of'",
        "href": "AIP/quality-rules/7922",
        "status": null,
        "critical": false,
        "technologyNames": [
            "C++"
        ]
    },
    {
        "id": 7924,
        "name": "Avoid defining Functions with 'struct' or 'class' parameters passed by value",
        "href": "AIP/quality-rules/7924",
        "status": null,
        "critical": false,
        "technologyNames": [
            "C",
            "C++"
        ]
    },
    {
        "id": 7930,
        "name": "Avoid redeclaring and overriding Methods with different default parameter values",
        "href": "AIP/quality-rules/7930",
        "status": null,
        "critical": false,
        "technologyNames": [
            "C++"
        ]
    },
    {
        "id": 7936,
        "name": "Avoid using finalize()",
        "href": "AIP/quality-rules/7936",
        "status": null,
        "critical": true,
        "technologyNames": [
            "JEE"
        ]
    },
    {
        "id": 7938,
        "name": "Override all overloads of a base Class virtual Method",
        "href": "AIP/quality-rules/7938",
        "status": null,
        "critical": false,
        "technologyNames": [
            "C++"
        ]
    },
    {
        "id": 7940,
        "name": "Avoid Stateful Beans not removed",
        "href": "AIP/quality-rules/7940",
        "status": null,
        "critical": true,
        "technologyNames": [
            "JEE"
        ]
    },
    {
        "id": 7966,
        "name": "Avoid includes in Header Files",
        "href": "AIP/quality-rules/7966",
        "status": null,
        "critical": false,
        "technologyNames": [
            "C",
            "C++"
        ]
    },
    {
        "id": 7968,
        "name": "Never use strcat() function (C/C++)",
        "href": "AIP/quality-rules/7968",
        "status": null,
        "critical": false,
        "technologyNames": [
            "C",
            "C++"
        ]
    },
    {
        "id": 7970,
        "name": "Never use strcpy() function (C/C++)",
        "href": "AIP/quality-rules/7970",
        "status": null,
        "critical": false,
        "technologyNames": [
            "C",
            "C++"
        ]
    },
    {
        "id": 7972,
        "name": "Never use sprintf() or vsprintf() functions",
        "href": "AIP/quality-rules/7972",
        "status": null,
        "critical": false,
        "technologyNames": [
            "C",
            "C++"
        ]
    },
    {
        "id": 7976,
        "name": "Never use gets() function",
        "href": "AIP/quality-rules/7976",
        "status": null,
        "critical": false,
        "technologyNames": [
            "C",
            "C++"
        ]
    },
    {
        "id": 7978,
        "name": "Avoid using the scanf() function family",
        "href": "AIP/quality-rules/7978",
        "status": null,
        "critical": false,
        "technologyNames": [
            "C",
            "C++"
        ]
    },
    {
        "id": 7980,
        "name": "Avoid using strtrns() function",
        "href": "AIP/quality-rules/7980",
        "status": null,
        "critical": false,
        "technologyNames": [
            "C",
            "C++"
        ]
    },
    {
        "id": 7982,
        "name": "Avoid using strlen() function family",
        "href": "AIP/quality-rules/7982",
        "status": null,
        "critical": false,
        "technologyNames": [
            "C",
            "C++"
        ]
    },
    {
        "id": 7984,
        "name": "Avoid using strecpy() function",
        "href": "AIP/quality-rules/7984",
        "status": null,
        "critical": false,
        "technologyNames": [
            "C",
            "C++"
        ]
    },
    {
        "id": 7986,
        "name": "Avoid using streadd() function",
        "href": "AIP/quality-rules/7986",
        "status": null,
        "critical": false,
        "technologyNames": [
            "C",
            "C++"
        ]
    },
    {
        "id": 7988,
        "name": "Avoid using snprintf() function family",
        "href": "AIP/quality-rules/7988",
        "status": null,
        "critical": false,
        "technologyNames": [
            "C",
            "C++"
        ]
    },
    {
        "id": 7990,
        "name": "Avoid using realpath() function",
        "href": "AIP/quality-rules/7990",
        "status": null,
        "critical": false,
        "technologyNames": [
            "C",
            "C++"
        ]
    },
    {
        "id": 7992,
        "name": "Avoid using getpass() function",
        "href": "AIP/quality-rules/7992",
        "status": null,
        "critical": false,
        "technologyNames": [
            "C",
            "C++"
        ]
    },
    {
        "id": 7994,
        "name": "Avoid using getopt() function",
        "href": "AIP/quality-rules/7994",
        "status": null,
        "critical": false,
        "technologyNames": [
            "C",
            "C++"
        ]
    },
    {
        "id": 7996,
        "name": "Provide a private default Constructor for utility Classes or use free Functions in a Namespace",
        "href": "AIP/quality-rules/7996",
        "status": null,
        "critical": false,
        "technologyNames": [
            "C++"
        ]
    },
    {
        "id": 8000,
        "name": "Avoid 'catch-all' statement",
        "href": "AIP/quality-rules/8000",
        "status": null,
        "critical": false,
        "technologyNames": [
            "C++"
        ]
    },
    {
        "id": 8010,
        "name": "Do not overload the ampersand, comma, logical AND or logical OR operators",
        "href": "AIP/quality-rules/8010",
        "status": null,
        "critical": false,
        "technologyNames": [
            "C++"
        ]
    },
    {
        "id": 8016,
        "name": "Avoid unsecured EJB remote method",
        "href": "AIP/quality-rules/8016",
        "status": null,
        "critical": true,
        "technologyNames": [
            "JEE"
        ]
    },
    {
        "id": 8028,
        "name": "Avoid missing default in switch statements",
        "href": "AIP/quality-rules/8028",
        "status": null,
        "critical": false,
        "technologyNames": [
            "C",
            "C++",
            "HTML5",
            "JEE"
        ]
    },
    {
        "id": 8032,
        "name": "Avoid using a break statement in 'for' loops",
        "href": "AIP/quality-rules/8032",
        "status": null,
        "critical": false,
        "technologyNames": [
            "C",
            "C++",
            "HTML5",
            "JEE"
        ]
    },
    {
        "id": 8038,
        "name": "Avoid Struts 2 Validator field not referencing a java class field",
        "href": "AIP/quality-rules/8038",
        "status": null,
        "critical": false,
        "technologyNames": [
            "JEE"
        ]
    },
    {
        "id": 8042,
        "name": "Struts 2 Validation: Avoid unused validation form",
        "href": "AIP/quality-rules/8042",
        "status": null,
        "critical": false,
        "technologyNames": [
            "JEE"
        ]
    },
    {
        "id": 8044,
        "name": "Avoid log forging vulnerabilities",
        "href": "AIP/quality-rules/8044",
        "status": null,
        "critical": true,
        "technologyNames": [
            "JEE"
        ]
    },
    {
        "id": 8046,
        "name": "Do not return non-const handles to Class data from const member Functions",
        "href": "AIP/quality-rules/8046",
        "status": null,
        "critical": false,
        "technologyNames": [
            "C",
            "C++"
        ]
    },
    {
        "id": 8048,
        "name": "Invoke 'delete' with the same form as the matching 'new'",
        "href": "AIP/quality-rules/8048",
        "status": null,
        "critical": true,
        "technologyNames": [
            "C",
            "C++"
        ]
    },
    {
        "id": 8050,
        "name": "Do not hide declarations in other scopes",
        "href": "AIP/quality-rules/8050",
        "status": null,
        "critical": false,
        "technologyNames": [
            "C",
            "C++"
        ]
    },
    {
        "id": 8058,
        "name": "A pointer to a derived Class shall only be cast implicitly to a pointer to base Class",
        "href": "AIP/quality-rules/8058",
        "status": null,
        "critical": false,
        "technologyNames": [
            "C",
            "C++"
        ]
    },
    {
        "id": 8060,
        "name": "A pointer to a base Class shall only be cast to a pointer to a derived Class by means of 'dynamic_cast'",
        "href": "AIP/quality-rules/8060",
        "status": null,
        "critical": false,
        "technologyNames": [
            "C",
            "C++"
        ]
    },
    {
        "id": 8062,
        "name": "An unconditional 'throw', 'return' or 'break' shall terminate every non-empty switch-clause",
        "href": "AIP/quality-rules/8062",
        "status": null,
        "critical": false,
        "technologyNames": [
            "C",
            "C++"
        ]
    },
    {
        "id": 8066,
        "name": "Avoid using 'using namespace' or 'using' declarations in header files",
        "href": "AIP/quality-rules/8066",
        "status": null,
        "critical": false,
        "technologyNames": [
            "C",
            "C++"
        ]
    },
    {
        "id": 8068,
        "name": "Do not return a dereferenced pointer allocated inside the function",
        "href": "AIP/quality-rules/8068",
        "status": null,
        "critical": true,
        "technologyNames": [
            "C",
            "C++"
        ]
    },
    {
        "id": 8070,
        "name": "Do not alter a control variable in the body of a 'for' statement",
        "href": "AIP/quality-rules/8070",
        "status": null,
        "critical": false,
        "technologyNames": [
            "C",
            "C++"
        ]
    },
    {
        "id": 8076,
        "name": "Avoid using 'new[]', prefer 'std::vector' or 'std::array'",
        "href": "AIP/quality-rules/8076",
        "status": null,
        "critical": false,
        "technologyNames": [
            "C",
            "C++"
        ]
    },
    {
        "id": 8078,
        "name": "Casting from pointer to base Class to pointer to derived Class should be done through 'dynamic_cast' or 'static_cast'",
        "href": "AIP/quality-rules/8078",
        "status": null,
        "critical": false,
        "technologyNames": [
            "C",
            "C++"
        ]
    },
    {
        "id": 8098,
        "name": "Avoid uncontrolled format string",
        "href": "AIP/quality-rules/8098",
        "status": null,
        "critical": true,
        "technologyNames": [
            "JEE"
        ]
    },
    {
        "id": 8100,
        "name": "Blocking synchronous calls should have associated timeouts",
        "href": "AIP/quality-rules/8100",
        "status": null,
        "critical": false,
        "technologyNames": [
            "JEE"
        ]
    },
    {
        "id": 8104,
        "name": "Close database resources ASAP",
        "href": "AIP/quality-rules/8104",
        "status": null,
        "critical": true,
        "technologyNames": [
            "JEE"
        ]
    },
    {
        "id": 8108,
        "name": "Close the outermost stream ASAP",
        "href": "AIP/quality-rules/8108",
        "status": null,
        "critical": true,
        "technologyNames": [
            "JEE"
        ]
    },
    {
        "id": 8110,
        "name": "Use dedicated stored procedures when multiple data accesses are needed (ASCPEM-PRF-10)",
        "href": "AIP/quality-rules/8110",
        "status": null,
        "critical": true,
        "technologyNames": [
            "JEE"
        ]
    },
    {
        "id": 8112,
        "name": "Avoid improper processing of the execution status of data handling operations",
        "href": "AIP/quality-rules/8112",
        "status": null,
        "critical": true,
        "technologyNames": [
            "JEE"
        ]
    },
    {
        "id": 8214,
        "name": "Expired or Released Resource should not be used",
        "href": "AIP/quality-rules/8214",
        "status": null,
        "critical": true,
        "technologyNames": [
            "JEE"
        ]
    },
    {
        "id": 8222,
        "name": "Avoid hard-coded credentials",
        "href": "AIP/quality-rules/8222",
        "status": null,
        "critical": true,
        "technologyNames": [
            "JEE"
        ]
    },
    {
        "id": 8238,
        "name": "Avoid mixing trusted and untrusted data in HTTP requests",
        "href": "AIP/quality-rules/8238",
        "status": null,
        "critical": true,
        "technologyNames": [
            "JEE"
        ]
    },
    {
        "id": 8240,
        "name": "Sensitive cookie in HTTPS session without 'Secure' attribute",
        "href": "AIP/quality-rules/8240",
        "status": null,
        "critical": true,
        "technologyNames": [
            "JEE"
        ]
    },
    {
        "id": 8242,
        "name": "Use of insufficiently random values",
        "href": "AIP/quality-rules/8242",
        "status": null,
        "critical": true,
        "technologyNames": [
            "JEE"
        ]
    },
    {
        "id": 8408,
        "name": "Avoid reflected cross-site scripting (non persistent)",
        "href": "AIP/quality-rules/8408",
        "status": null,
        "critical": true,
        "technologyNames": [
            "JEE"
        ]
    },
    {
        "id": 8410,
        "name": "Avoid cross-site scripting (persistent)",
        "href": "AIP/quality-rules/8410",
        "status": null,
        "critical": true,
        "technologyNames": [
            "JEE"
        ]
    },
    {
        "id": 8420,
        "name": "Avoid second order SQL injection",
        "href": "AIP/quality-rules/8420",
        "status": null,
        "critical": true,
        "technologyNames": [
            "JEE"
        ]
    },
    {
        "id": 1020022,
        "name": "Avoid using submitted markup containing \"form\" and \"formaction\" attributes",
        "href": "AIP/quality-rules/1020022",
        "status": null,
        "critical": true,
        "technologyNames": [
            "HTML5"
        ]
    },
    {
        "id": 1020024,
        "name": "Avoid using submit markup related to \"form\" with id attribute",
        "href": "AIP/quality-rules/1020024",
        "status": null,
        "critical": true,
        "technologyNames": [
            "HTML5"
        ]
    },
    {
        "id": 1020026,
        "name": "Avoid using autofocus and onfocus in submitted markup",
        "href": "AIP/quality-rules/1020026",
        "status": null,
        "critical": true,
        "technologyNames": [
            "HTML5"
        ]
    },
    {
        "id": 1020028,
        "name": "Avoid using autofocus and onblur in submitted markup",
        "href": "AIP/quality-rules/1020028",
        "status": null,
        "critical": true,
        "technologyNames": [
            "HTML5"
        ]
    },
    {
        "id": 1020030,
        "name": "Avoid using javascript or expression in the CSS file",
        "href": "AIP/quality-rules/1020030",
        "status": null,
        "critical": true,
        "technologyNames": [
            "HTML5"
        ]
    },
    {
        "id": 1020032,
        "name": "Avoid using video poster attributes in combination with javascript",
        "href": "AIP/quality-rules/1020032",
        "status": null,
        "critical": true,
        "technologyNames": [
            "HTML5"
        ]
    },
    {
        "id": 1020034,
        "name": "Avoid hosting HTML code in iframe srcdoc",
        "href": "AIP/quality-rules/1020034",
        "status": null,
        "critical": true,
        "technologyNames": [
            "HTML5"
        ]
    },
    {
        "id": 1020036,
        "name": "Avoid using onscroll event with autofocus input",
        "href": "AIP/quality-rules/1020036",
        "status": null,
        "critical": true,
        "technologyNames": [
            "HTML5"
        ]
    },
    {
        "id": 1020038,
        "name": "Avoid defining and calling functions inside loops",
        "href": "AIP/quality-rules/1020038",
        "status": null,
        "critical": false,
        "technologyNames": [
            "HTML5"
        ]
    },
    {
        "id": 1020042,
        "name": "Avoid having iframe inside a tag",
        "href": "AIP/quality-rules/1020042",
        "status": null,
        "critical": true,
        "technologyNames": [
            "HTML5"
        ]
    },
    {
        "id": 1020044,
        "name": "Avoid using setData in ondragstart with attribute draggable set to true",
        "href": "AIP/quality-rules/1020044",
        "status": null,
        "critical": true,
        "technologyNames": [
            "HTML5"
        ]
    },
    {
        "id": 1020046,
        "name": "Avoid using oninput in body containing input autofocus",
        "href": "AIP/quality-rules/1020046",
        "status": null,
        "critical": true,
        "technologyNames": [
            "HTML5"
        ]
    },
    {
        "id": 1020048,
        "name": "Avoid using source tag in video/audio with event handler",
        "href": "AIP/quality-rules/1020048",
        "status": null,
        "critical": true,
        "technologyNames": [
            "HTML5"
        ]
    },
    {
        "id": 1020050,
        "name": "Avoid white-listing the \"dirname\" attribute in user generated content",
        "href": "AIP/quality-rules/1020050",
        "status": null,
        "critical": true,
        "technologyNames": [
            "HTML5"
        ]
    },
    {
        "id": 1020052,
        "name": "Avoid using import with external URI",
        "href": "AIP/quality-rules/1020052",
        "status": null,
        "critical": true,
        "technologyNames": [
            "HTML5"
        ]
    },
    {
        "id": 1020056,
        "name": "Avoid using Javascript Document.all collection",
        "href": "AIP/quality-rules/1020056",
        "status": null,
        "critical": false,
        "technologyNames": [
            "HTML5"
        ]
    },
    {
        "id": 1020058,
        "name": "Avoid using eval() (Javascript)",
        "href": "AIP/quality-rules/1020058",
        "status": null,
        "critical": true,
        "technologyNames": [
            "HTML5"
        ]
    },
    {
        "id": 1020060,
        "name": "Avoid using console.log()",
        "href": "AIP/quality-rules/1020060",
        "status": null,
        "critical": false,
        "technologyNames": [
            "HTML5"
        ]
    },
    {
        "id": 1020062,
        "name": "Avoid using non thread-safe Javascript singleton pattern",
        "href": "AIP/quality-rules/1020062",
        "status": null,
        "critical": false,
        "technologyNames": [
            "HTML5"
        ]
    },
    {
        "id": 1020064,
        "name": "Avoid Superclass knowing Subclass (Javascript)",
        "href": "AIP/quality-rules/1020064",
        "status": null,
        "critical": false,
        "technologyNames": [
            "HTML5"
        ]
    },
    {
        "id": 1020068,
        "name": "Avoid return statement in finally block (Javascript)",
        "href": "AIP/quality-rules/1020068",
        "status": null,
        "critical": true,
        "technologyNames": [
            "HTML5"
        ]
    },
    {
        "id": 1020074,
        "name": "Avoid enabling autocomplete \"on\" for inputs/forms",
        "href": "AIP/quality-rules/1020074",
        "status": null,
        "critical": false,
        "technologyNames": [
            "HTML5"
        ]
    },
    {
        "id": 1020076,
        "name": "Avoid Artifacts with too many parameters (Javascript)",
        "href": "AIP/quality-rules/1020076",
        "status": null,
        "critical": false,
        "technologyNames": [
            "HTML5"
        ]
    },
    {
        "id": 1020078,
        "name": "Avoid using setTimeout()",
        "href": "AIP/quality-rules/1020078",
        "status": null,
        "critical": true,
        "technologyNames": [
            "HTML5"
        ]
    },
    {
        "id": 1020080,
        "name": "Avoid using setInterval()",
        "href": "AIP/quality-rules/1020080",
        "status": null,
        "critical": true,
        "technologyNames": [
            "HTML5"
        ]
    },
    {
        "id": 1020090,
        "name": "Avoid Artifacts with High Depth of Code (Javascript)",
        "href": "AIP/quality-rules/1020090",
        "status": null,
        "critical": false,
        "technologyNames": [
            "HTML5"
        ]
    },
    {
        "id": 1020092,
        "name": "Avoid direct definition of JavaScript Functions in a Web page (Javascript/HTML5)",
        "href": "AIP/quality-rules/1020092",
        "status": null,
        "critical": false,
        "technologyNames": [
            "HTML5"
        ]
    },
    {
        "id": 1020094,
        "name": "Avoid creating cookie without setting httpOnly option (Javascript)",
        "href": "AIP/quality-rules/1020094",
        "status": null,
        "critical": true,
        "technologyNames": [
            "HTML5"
        ]
    },
    {
        "id": 1020096,
        "name": "Avoid using unsecured cookie (Javascript)",
        "href": "AIP/quality-rules/1020096",
        "status": null,
        "critical": true,
        "technologyNames": [
            "HTML5"
        ]
    },
    {
        "id": 1020098,
        "name": "Avoid creating cookie with overly broad path (Javascript)",
        "href": "AIP/quality-rules/1020098",
        "status": null,
        "critical": true,
        "technologyNames": [
            "HTML5"
        ]
    },
    {
        "id": 1020100,
        "name": "Avoid having cookie with an overly broad domain (Javascript)",
        "href": "AIP/quality-rules/1020100",
        "status": null,
        "critical": true,
        "technologyNames": [
            "HTML5"
        ]
    },
    {
        "id": 1020102,
        "name": "Always use JSON.parse & JSON.stringify with try/catch block (Javascript)",
        "href": "AIP/quality-rules/1020102",
        "status": null,
        "critical": false,
        "technologyNames": [
            "HTML5"
        ]
    },
    {
        "id": 1020104,
        "name": "Avoid hardcoded passwords (Javascript)",
        "href": "AIP/quality-rules/1020104",
        "status": null,
        "critical": true,
        "technologyNames": [
            "HTML5"
        ]
    },
    {
        "id": 1020300,
        "name": "Avoid using the call of web service jQuery ajax inside a loop",
        "href": "AIP/quality-rules/1020300",
        "status": null,
        "critical": true,
        "technologyNames": [
            "HTML5"
        ]
    },
    {
        "id": 1020302,
        "name": "Avoid using element type in jQuery",
        "href": "AIP/quality-rules/1020302",
        "status": null,
        "critical": false,
        "technologyNames": [
            "HTML5"
        ]
    },
    {
        "id": 1020304,
        "name": "Implement success and error or complete callbacks when using jquery web service call before jQuery 3.0",
        "href": "AIP/quality-rules/1020304",
        "status": null,
        "critical": true,
        "technologyNames": [
            "HTML5"
        ]
    },
    {
        "id": 1020306,
        "name": "Always use find for Id->Child nested selectors",
        "href": "AIP/quality-rules/1020306",
        "status": null,
        "critical": false,
        "technologyNames": [
            "HTML5"
        ]
    },
    {
        "id": 1020308,
        "name": "Always cache the returned objects in variables to be reused",
        "href": "AIP/quality-rules/1020308",
        "status": null,
        "critical": false,
        "technologyNames": [
            "HTML5"
        ]
    },
    {
        "id": 1020310,
        "name": "Use \"type=\" to select elements by type",
        "href": "AIP/quality-rules/1020310",
        "status": null,
        "critical": false,
        "technologyNames": [
            "HTML5"
        ]
    },
    {
        "id": 1020314,
        "name": "Avoid using css() of many elements",
        "href": "AIP/quality-rules/1020314",
        "status": null,
        "critical": false,
        "technologyNames": [
            "HTML5"
        ]
    },
    {
        "id": 1020316,
        "name": "Avoid Universal Selectors",
        "href": "AIP/quality-rules/1020316",
        "status": null,
        "critical": false,
        "technologyNames": [
            "HTML5"
        ]
    },
    {
        "id": 1020320,
        "name": "Avoid using jQuery $.cookie",
        "href": "AIP/quality-rules/1020320",
        "status": null,
        "critical": false,
        "technologyNames": [
            "HTML5"
        ]
    },
    {
        "id": 1020326,
        "name": "Always implement done, fail and/or always callbacks for $.ajax calls when using jQuery 3.0 (and latest)",
        "href": "AIP/quality-rules/1020326",
        "status": null,
        "critical": false,
        "technologyNames": [
            "HTML5"
        ]
    },
    {
        "id": 1020450,
        "name": "Ensure catching Javascript error in React components",
        "href": "AIP/quality-rules/1020450",
        "status": null,
        "critical": false,
        "technologyNames": [
            "HTML5"
        ]
    },
    {
        "id": 1020452,
        "name": "Avoid empty componentDidCatch blocks",
        "href": "AIP/quality-rules/1020452",
        "status": null,
        "critical": true,
        "technologyNames": [
            "HTML5"
        ]
    },
    {
        "id": 1020454,
        "name": "Avoid using React dangerouslySetInnerHTML",
        "href": "AIP/quality-rules/1020454",
        "status": null,
        "critical": true,
        "technologyNames": [
            "HTML5"
        ]
    },
    {
        "id": 1020456,
        "name": "Avoid using \"<script>\" tag in HTML template used by React.js components",
        "href": "AIP/quality-rules/1020456",
        "status": null,
        "critical": false,
        "technologyNames": [
            "HTML5"
        ]
    },
    {
        "id": 1020500,
        "name": "Avoid the use of the default JavaScript implementation [].forEach in AngularJS web app",
        "href": "AIP/quality-rules/1020500",
        "status": null,
        "critical": false,
        "technologyNames": [
            "HTML5"
        ]
    },
    {
        "id": 1020504,
        "name": "Avoid using the call of web service with AngularJS $http inside a loop",
        "href": "AIP/quality-rules/1020504",
        "status": null,
        "critical": true,
        "technologyNames": [
            "HTML5"
        ]
    },
    {
        "id": 1020506,
        "name": "Avoid using $scope in controllers",
        "href": "AIP/quality-rules/1020506",
        "status": null,
        "critical": false,
        "technologyNames": [
            "HTML5"
        ]
    },
    {
        "id": 1020508,
        "name": "Use Angular wrapper service $document",
        "href": "AIP/quality-rules/1020508",
        "status": null,
        "critical": false,
        "technologyNames": [
            "HTML5"
        ]
    },
    {
        "id": 1020510,
        "name": "Use Angular wrapper service $window",
        "href": "AIP/quality-rules/1020510",
        "status": null,
        "critical": false,
        "technologyNames": [
            "HTML5"
        ]
    },
    {
        "id": 1020512,
        "name": "Use Angular wrapper service $timeout",
        "href": "AIP/quality-rules/1020512",
        "status": null,
        "critical": false,
        "technologyNames": [
            "HTML5"
        ]
    },
    {
        "id": 1020516,
        "name": "Avoid using Javascript Array typecheck in AngularJS application",
        "href": "AIP/quality-rules/1020516",
        "status": null,
        "critical": false,
        "technologyNames": [
            "HTML5"
        ]
    },
    {
        "id": 1020518,
        "name": "Avoid using Javascript Date typecheck in AngularJS application",
        "href": "AIP/quality-rules/1020518",
        "status": null,
        "critical": false,
        "technologyNames": [
            "HTML5"
        ]
    },
    {
        "id": 1020520,
        "name": "Avoid using Javascript Function typecheck in AngularJS application",
        "href": "AIP/quality-rules/1020520",
        "status": null,
        "critical": false,
        "technologyNames": [
            "HTML5"
        ]
    },
    {
        "id": 1020522,
        "name": "Avoid using Javascript String typecheck in AngularJS application",
        "href": "AIP/quality-rules/1020522",
        "status": null,
        "critical": false,
        "technologyNames": [
            "HTML5"
        ]
    },
    {
        "id": 1020524,
        "name": "Avoid using Javascript Object typecheck in AngularJS application",
        "href": "AIP/quality-rules/1020524",
        "status": null,
        "critical": false,
        "technologyNames": [
            "HTML5"
        ]
    },
    {
        "id": 1020526,
        "name": "Avoid using Javascript Number typecheck in AngularJS application",
        "href": "AIP/quality-rules/1020526",
        "status": null,
        "critical": false,
        "technologyNames": [
            "HTML5"
        ]
    },
    {
        "id": 1020528,
        "name": "Avoid using Javascript Regexp typecheck in AngularJS application",
        "href": "AIP/quality-rules/1020528",
        "status": null,
        "critical": false,
        "technologyNames": [
            "HTML5"
        ]
    },
    {
        "id": 1020532,
        "name": "Use Angular factory() instead of service()",
        "href": "AIP/quality-rules/1020532",
        "status": null,
        "critical": false,
        "technologyNames": [
            "HTML5"
        ]
    },
    {
        "id": 1020534,
        "name": "Avoid using a web service with AngularJS $resource inside a loop",
        "href": "AIP/quality-rules/1020534",
        "status": null,
        "critical": true,
        "technologyNames": [
            "HTML5"
        ]
    },
    {
        "id": 1020540,
        "name": "Avoid using $http success and error function",
        "href": "AIP/quality-rules/1020540",
        "status": null,
        "critical": false,
        "technologyNames": [
            "HTML5"
        ]
    },
    {
        "id": 1020542,
        "name": "Enable Content Security Policy when creating an AngularJS application",
        "href": "AIP/quality-rules/1020542",
        "status": null,
        "critical": true,
        "technologyNames": [
            "HTML5"
        ]
    },
    {
        "id": 1020544,
        "name": "Avoid disabling Strict Contextual Escaping (SCE) when created",
        "href": "AIP/quality-rules/1020544",
        "status": null,
        "critical": true,
        "technologyNames": [
            "HTML5"
        ]
    },
    {
        "id": 1020546,
        "name": "Avoid using unsanitized AngularJS application",
        "href": "AIP/quality-rules/1020546",
        "status": null,
        "critical": true,
        "technologyNames": [
            "HTML5"
        ]
    },
    {
        "id": 1020548,
        "name": "Avoid disabling withCredentials option for the httpProvider",
        "href": "AIP/quality-rules/1020548",
        "status": null,
        "critical": true,
        "technologyNames": [
            "HTML5"
        ]
    },
    {
        "id": 1020550,
        "name": "Avoid using \"ng-repeat\" loop without \"track by\" option",
        "href": "AIP/quality-rules/1020550",
        "status": null,
        "critical": false,
        "technologyNames": [
            "HTML5"
        ]
    },
    {
        "id": 1020552,
        "name": "Avoid enabling dangerous protocols in whitelist APIs",
        "href": "AIP/quality-rules/1020552",
        "status": null,
        "critical": false,
        "technologyNames": [
            "HTML5"
        ]
    },
    {
        "id": 1020700,
        "name": "Avoid the lack of error handling in the Node.js callbacks",
        "href": "AIP/quality-rules/1020700",
        "status": null,
        "critical": false,
        "technologyNames": [
            "HTML5"
        ]
    },
    {
        "id": 1020702,
        "name": "Avoid using process.exit() without defining exitCode",
        "href": "AIP/quality-rules/1020702",
        "status": null,
        "critical": false,
        "technologyNames": [
            "HTML5"
        ]
    },
    {
        "id": 1020706,
        "name": "Ensure the Content-Security-Policy is activated (Node.js)",
        "href": "AIP/quality-rules/1020706",
        "status": null,
        "critical": true,
        "technologyNames": [
            "HTML5"
        ]
    },
    {
        "id": 1020708,
        "name": "Ensure the X-Powered-By header is disabled",
        "href": "AIP/quality-rules/1020708",
        "status": null,
        "critical": true,
        "technologyNames": [
            "HTML5"
        ]
    },
    {
        "id": 1020710,
        "name": "Ensure the X-XSS-Protection header is enabled",
        "href": "AIP/quality-rules/1020710",
        "status": null,
        "critical": true,
        "technologyNames": [
            "HTML5"
        ]
    },
    {
        "id": 1020712,
        "name": "Ensure the X-Frame-Options header is setup (Node.js)",
        "href": "AIP/quality-rules/1020712",
        "status": null,
        "critical": true,
        "technologyNames": [
            "HTML5"
        ]
    },
    {
        "id": 1020714,
        "name": "Avoid having multiple routes for the same path with Node.js Express App",
        "href": "AIP/quality-rules/1020714",
        "status": null,
        "critical": true,
        "technologyNames": [
            "HTML5"
        ]
    },
    {
        "id": 1020716,
        "name": "Avoid using the call of web service with Node.js http.get or http.request inside a loop",
        "href": "AIP/quality-rules/1020716",
        "status": null,
        "critical": true,
        "technologyNames": [
            "HTML5"
        ]
    },
    {
        "id": 1020718,
        "name": "Ensure that browser cannot cache or store a page",
        "href": "AIP/quality-rules/1020718",
        "status": null,
        "critical": false,
        "technologyNames": [
            "HTML5"
        ]
    },
    {
        "id": 1020720,
        "name": "Allow only HTTPS communication",
        "href": "AIP/quality-rules/1020720",
        "status": null,
        "critical": true,
        "technologyNames": [
            "HTML5"
        ]
    },
    {
        "id": 1020722,
        "name": "Ensure to use secure HTTPS protocol",
        "href": "AIP/quality-rules/1020722",
        "status": null,
        "critical": true,
        "technologyNames": [
            "HTML5"
        ]
    },
    {
        "id": 1020724,
        "name": "Ensure that marked is sanitized",
        "href": "AIP/quality-rules/1020724",
        "status": null,
        "critical": true,
        "technologyNames": [
            "HTML5"
        ]
    },
    {
        "id": 1020726,
        "name": "Ensure that CSRF Protection is enabled (Node.js)",
        "href": "AIP/quality-rules/1020726",
        "status": null,
        "critical": true,
        "technologyNames": [
            "HTML5"
        ]
    },
    {
        "id": 1020728,
        "name": "Avoid creating cookie without setting httpOnly option (Node.js)",
        "href": "AIP/quality-rules/1020728",
        "status": null,
        "critical": true,
        "technologyNames": [
            "HTML5"
        ]
    },
    {
        "id": 1020730,
        "name": "Ensure Node.js filesystem are closed",
        "href": "AIP/quality-rules/1020730",
        "status": null,
        "critical": false,
        "technologyNames": [
            "HTML5"
        ]
    },
    {
        "id": 1020734,
        "name": "Avoid using unsecured cookie (Node.js)",
        "href": "AIP/quality-rules/1020734",
        "status": null,
        "critical": true,
        "technologyNames": [
            "HTML5"
        ]
    },
    {
        "id": 1020736,
        "name": "Avoid bypassing self-signed ssl certificate (Node.js)",
        "href": "AIP/quality-rules/1020736",
        "status": null,
        "critical": true,
        "technologyNames": [
            "HTML5"
        ]
    },
    {
        "id": 1020738,
        "name": "Avoid disabling SSL verification in node-curl",
        "href": "AIP/quality-rules/1020738",
        "status": null,
        "critical": true,
        "technologyNames": [
            "HTML5"
        ]
    },
    {
        "id": 1020740,
        "name": "Avoid creating cookie with overly broad path (Node.js)",
        "href": "AIP/quality-rules/1020740",
        "status": null,
        "critical": true,
        "technologyNames": [
            "HTML5"
        ]
    },
    {
        "id": 1020742,
        "name": "Avoid creating cookie with overly broad domain (Node.js)",
        "href": "AIP/quality-rules/1020742",
        "status": null,
        "critical": false,
        "technologyNames": [
            "HTML5"
        ]
    },
    {
        "id": 1020748,
        "name": "Avoid using the call of data service with Node.js inside a loop",
        "href": "AIP/quality-rules/1020748",
        "status": null,
        "critical": true,
        "technologyNames": [
            "HTML5"
        ]
    },
    {
        "id": 1020800,
        "name": "Avoid jump statements in finally ",
        "href": "AIP/quality-rules/1020800",
        "status": null,
        "critical": false,
        "technologyNames": [
            "HTML5"
        ]
    },
    {
        "id": 1020802,
        "name": "Avoid having errors without throwing them ",
        "href": "AIP/quality-rules/1020802",
        "status": null,
        "critical": false,
        "technologyNames": [
            "HTML5"
        ]
    },
    {
        "id": 1020804,
        "name": "Avoid using console logging ",
        "href": "AIP/quality-rules/1020804",
        "status": null,
        "critical": false,
        "technologyNames": [
            "HTML5"
        ]
    },
    {
        "id": 1020808,
        "name": "Avoid using eval() (Typescript)",
        "href": "AIP/quality-rules/1020808",
        "status": null,
        "critical": true,
        "technologyNames": [
            "HTML5"
        ]
    },
    {
        "id": 1020810,
        "name": "Avoid bypassing angular security trust ",
        "href": "AIP/quality-rules/1020810",
        "status": null,
        "critical": true,
        "technologyNames": [
            "HTML5"
        ]
    },
    {
        "id": 1020812,
        "name": "Avoid invoking super more than once in constructor ",
        "href": "AIP/quality-rules/1020812",
        "status": null,
        "critical": false,
        "technologyNames": [
            "HTML5"
        ]
    },
    {
        "id": 1020814,
        "name": "Avoid using web service calls inside a loop",
        "href": "AIP/quality-rules/1020814",
        "status": null,
        "critical": true,
        "technologyNames": [
            "HTML5"
        ]
    },
    {
        "id": 1020818,
        "name": "Avoid disabling xsrf check in HttpClientXsrfModule",
        "href": "AIP/quality-rules/1020818",
        "status": null,
        "critical": true,
        "technologyNames": [
            "HTML5"
        ]
    },
    {
        "id": 1020820,
        "name": "Avoid hardcoded passwords (TypeScript)",
        "href": "AIP/quality-rules/1020820",
        "status": null,
        "critical": true,
        "technologyNames": [
            "HTML5"
        ]
    },
    {
        "id": 1020822,
        "name": "Always provide error callbacks when subscribing to HttpClient observables",
        "href": "AIP/quality-rules/1020822",
        "status": null,
        "critical": false,
        "technologyNames": [
            "HTML5"
        ]
    },
    {
        "id": 1020824,
        "name": "Avoid Superclass knowing Subclass (Typescript)",
        "href": "AIP/quality-rules/1020824",
        "status": null,
        "critical": false,
        "technologyNames": [
            "HTML5"
        ]
    },
    {
        "id": 1020828,
        "name": "Avoid String concatenation in loops",
        "href": "AIP/quality-rules/1020828",
        "status": null,
        "critical": false,
        "technologyNames": [
            "HTML5"
        ]
    },
    {
        "id": 1020832,
        "name": "Avoid using javascript HTTP request in Angular Application",
        "href": "AIP/quality-rules/1020832",
        "status": null,
        "critical": true,
        "technologyNames": [
            "HTML5"
        ]
    },
    {
        "id": 1020834,
        "name": "Avoid using \"<script>\" tag into HTML template used by Angular Application",
        "href": "AIP/quality-rules/1020834",
        "status": null,
        "critical": false,
        "technologyNames": [
            "HTML5"
        ]
    },
    {
        "id": 1020836,
        "name": "Avoid exporting namespaces",
        "href": "AIP/quality-rules/1020836",
        "status": null,
        "critical": false,
        "technologyNames": [
            "HTML5"
        ]
    },
    {
        "id": 1020838,
        "name": "Avoid using Rx.observable.fromEvent without having a debouncetime set",
        "href": "AIP/quality-rules/1020838",
        "status": null,
        "critical": false,
        "technologyNames": [
            "HTML5"
        ]
    },
    {
        "id": 1020840,
        "name": "Avoid using ngFor loop without TrackBy option",
        "href": "AIP/quality-rules/1020840",
        "status": null,
        "critical": false,
        "technologyNames": [
            "HTML5"
        ]
    },
    {
        "id": 1020848,
        "name": "Always favour pipable operators in RxJS",
        "href": "AIP/quality-rules/1020848",
        "status": null,
        "critical": false,
        "technologyNames": [
            "HTML5"
        ]
    },
    {
        "id": 1020950,
        "name": "Avoid providing password in Web Service URL",
        "href": "AIP/quality-rules/1020950",
        "status": null,
        "critical": true,
        "technologyNames": [
            "ALL TECHNOLOGIES"
        ]
    },
    {
        "id": 1039006,
        "name": "Avoid using predictable SecureRandom Seeds",
        "href": "AIP/quality-rules/1039006",
        "status": null,
        "critical": true,
        "technologyNames": [
            "JEE"
        ]
    },
    {
        "id": 1039012,
        "name": "Avoid using referer header field in HTTP request",
        "href": "AIP/quality-rules/1039012",
        "status": null,
        "critical": true,
        "technologyNames": [
            "JEE"
        ]
    },
    {
        "id": 1039016,
        "name": "Avoid Unvalidated URL Redirect",
        "href": "AIP/quality-rules/1039016",
        "status": null,
        "critical": true,
        "technologyNames": [
            "JEE"
        ]
    },
    {
        "id": 1039028,
        "name": "Avoid weak encryption providing not sufficient key size (JEE)",
        "href": "AIP/quality-rules/1039028",
        "status": null,
        "critical": true,
        "technologyNames": [
            "JEE"
        ]
    },
    {
        "id": 1039032,
        "name": "Avoid using DocumentBuilder without restriction of XML External Entity Reference (XXE)",
        "href": "AIP/quality-rules/1039032",
        "status": null,
        "critical": true,
        "technologyNames": [
            "JEE"
        ]
    },
    {
        "id": 1039034,
        "name": "Avoid using SAXParserFactory without restriction of XML External Entity Reference (XXE)",
        "href": "AIP/quality-rules/1039034",
        "status": null,
        "critical": true,
        "technologyNames": [
            "JEE"
        ]
    },
    {
        "id": 1039036,
        "name": "Avoid using XMLReader without restriction of XML External Entity Reference (XXE)",
        "href": "AIP/quality-rules/1039036",
        "status": null,
        "critical": true,
        "technologyNames": [
            "JEE"
        ]
    },
    {
        "id": 1039038,
        "name": "Avoid using XPathFactory without restriction of XML External Entity Reference (XXE)",
        "href": "AIP/quality-rules/1039038",
        "status": null,
        "critical": true,
        "technologyNames": [
            "JEE"
        ]
    },
    {
        "id": 1039040,
        "name": "Avoid using XMLStreamReader without restriction of XML External Entity Reference (XXE)",
        "href": "AIP/quality-rules/1039040",
        "status": null,
        "critical": true,
        "technologyNames": [
            "JEE"
        ]
    },
    {
        "id": 1039044,
        "name": "Avoid usage of BannedAPI when using ESAPI library",
        "href": "AIP/quality-rules/1039044",
        "status": null,
        "critical": false,
        "technologyNames": [
            "JEE"
        ]
    },
    {
        "id": 1039048,
        "name": "Always prefer to set Array designators \"[]\" on the type and not at variable",
        "href": "AIP/quality-rules/1039048",
        "status": null,
        "critical": false,
        "technologyNames": [
            "JEE"
        ]
    },
    {
        "id": 1039050,
        "name": "Add @Override on methods overriding or implementing a method declared in a super type",
        "href": "AIP/quality-rules/1039050",
        "status": null,
        "critical": false,
        "technologyNames": [
            "JEE"
        ]
    },
    {
        "id": 1040002,
        "name": "Avoid disabling Spring Security CSRF Protection",
        "href": "AIP/quality-rules/1040002",
        "status": null,
        "critical": true,
        "technologyNames": [
            "JEE"
        ]
    },
    {
        "id": 1040006,
        "name": "Ensure setting Content-Security-Policy for spring application.",
        "href": "AIP/quality-rules/1040006",
        "status": null,
        "critical": true,
        "technologyNames": [
            "JEE"
        ]
    },
    {
        "id": 1040008,
        "name": "Ensure declaring formLogin after requesting authorization and authentication",
        "href": "AIP/quality-rules/1040008",
        "status": null,
        "critical": true,
        "technologyNames": [
            "JEE"
        ]
    },
    {
        "id": 1040010,
        "name": "Always delete the cookies during the logout",
        "href": "AIP/quality-rules/1040010",
        "status": null,
        "critical": true,
        "technologyNames": [
            "JEE"
        ]
    },
    {
        "id": 1040012,
        "name": "HTTP user session must be invalidated during logout",
        "href": "AIP/quality-rules/1040012",
        "status": null,
        "critical": true,
        "technologyNames": [
            "JEE"
        ]
    },
    {
        "id": 1040016,
        "name": "PermitAll or user role should be specified to access URL(s) of the application",
        "href": "AIP/quality-rules/1040016",
        "status": null,
        "critical": true,
        "technologyNames": [
            "JEE"
        ]
    },
    {
        "id": 1040018,
        "name": "Ensure the X-Frame-Options header is setup (Spring)",
        "href": "AIP/quality-rules/1040018",
        "status": null,
        "critical": true,
        "technologyNames": [
            "JEE"
        ]
    },
    {
        "id": 1040022,
        "name": "Ensure to enable Spring Boot Admin MBean",
        "href": "AIP/quality-rules/1040022",
        "status": null,
        "critical": false,
        "technologyNames": [
            "JEE"
        ]
    },
    {
        "id": 1040024,
        "name": "Ensure Spring Boot Shutdown Actuator Endpoint is disabled",
        "href": "AIP/quality-rules/1040024",
        "status": null,
        "critical": true,
        "technologyNames": [
            "JEE"
        ]
    },
    {
        "id": 1040030,
        "name": "Avoid Using Generic Authentication Exception Class",
        "href": "AIP/quality-rules/1040030",
        "status": null,
        "critical": false,
        "technologyNames": [
            "JEE"
        ]
    },
    {
        "id": 1040032,
        "name": "Avoid Using ControllerAdvice And HandlerExceptionResolver simultaneously",
        "href": "AIP/quality-rules/1040032",
        "status": null,
        "critical": false,
        "technologyNames": [
            "JEE"
        ]
    },
    {
        "id": 1042004,
        "name": "Avoid Duplicate Struts validation forms with the same name",
        "href": "AIP/quality-rules/1042004",
        "status": null,
        "critical": false,
        "technologyNames": [
            "JEE"
        ]
    },
    {
        "id": 1042010,
        "name": "Avoid using ParametersInterceptor with 2.3.16 (and older)",
        "href": "AIP/quality-rules/1042010",
        "status": null,
        "critical": true,
        "technologyNames": [
            "JEE"
        ]
    },
    {
        "id": 1042016,
        "name": "Avoid Struts action Mapping with disabled validator ",
        "href": "AIP/quality-rules/1042016",
        "status": null,
        "critical": true,
        "technologyNames": [
            "JEE"
        ]
    },
    {
        "id": 1042022,
        "name": "Avoid using CookieInterceptor with  2.3.16 (and Older)",
        "href": "AIP/quality-rules/1042022",
        "status": null,
        "critical": true,
        "technologyNames": [
            "JEE"
        ]
    },
    {
        "id": 1042024,
        "name": "Avoid Unescaped User-controlled Input attribute in Struts which Causes XSS",
        "href": "AIP/quality-rules/1042024",
        "status": null,
        "critical": true,
        "technologyNames": [
            "JEE"
        ]
    },
    {
        "id": 1042026,
        "name": "Avoid Action Mapping based on wildcards with Struts 2.3.14.2 and older versions",
        "href": "AIP/quality-rules/1042026",
        "status": null,
        "critical": true,
        "technologyNames": [
            "JEE"
        ]
    },
    {
        "id": 1042032,
        "name": "Avoid using setter on properties for the data coming from the user interface with Struts 2",
        "href": "AIP/quality-rules/1042032",
        "status": null,
        "critical": true,
        "technologyNames": [
            "JEE"
        ]
    },
    {
        "id": 1042034,
        "name": "Avoid using Struts REST plugin with XStream createXStream to deserialise XML requests in Struts 2.1.2 - Struts 2.3.33, Struts 2.5 - Struts 2.5.12",
        "href": "AIP/quality-rules/1042034",
        "status": null,
        "critical": true,
        "technologyNames": [
            "JEE"
        ]
    },
    {
        "id": 1065000,
        "name": "Avoid using \"continue\" statement",
        "href": "AIP/quality-rules/1065000",
        "status": null,
        "critical": false,
        "technologyNames": [
            "C",
            "C++"
        ]
    },
    {
        "id": 1065002,
        "name": "\"enum\" members other than the first one should not be explicitly initialized unless all members are explicitly initialized.",
        "href": "AIP/quality-rules/1065002",
        "status": null,
        "critical": false,
        "technologyNames": [
            "C",
            "C++"
        ]
    },
    {
        "id": 1065004,
        "name": "Ensure that dynamically allocated memory on local pointer in functions/methods is freed.",
        "href": "AIP/quality-rules/1065004",
        "status": null,
        "critical": false,
        "technologyNames": [
            "C",
            "C++"
        ]
    },
    {
        "id": 1065008,
        "name": "Avoid use of unvalidated input in array indexing and memory allocation",
        "href": "AIP/quality-rules/1065008",
        "status": null,
        "critical": false,
        "technologyNames": [
            "C",
            "C++"
        ]
    },
    {
        "id": 1101000,
        "name": "Never use SQL queries with a cartesian product (SQL)",
        "href": "AIP/quality-rules/1101000",
        "status": null,
        "critical": false,
        "technologyNames": [
            "ALL TECHNOLOGIES"
        ]
    },
    {
        "id": 1101002,
        "name": "Never use SQL queries with a cartesian product on XXL Tables (SQL)",
        "href": "AIP/quality-rules/1101002",
        "status": null,
        "critical": true,
        "technologyNames": [
            "ALL TECHNOLOGIES"
        ]
    },
    {
        "id": 1101004,
        "name": "Avoid non-indexed SQL queries",
        "href": "AIP/quality-rules/1101004",
        "status": null,
        "critical": false,
        "technologyNames": [
            "ALL TECHNOLOGIES"
        ]
    },
    {
        "id": 1101006,
        "name": "Avoid non-indexed XXL SQL queries",
        "href": "AIP/quality-rules/1101006",
        "status": null,
        "critical": true,
        "technologyNames": [
            "ALL TECHNOLOGIES"
        ]
    },
    {
        "id": 1101008,
        "name": "Avoid non-SARGable queries",
        "href": "AIP/quality-rules/1101008",
        "status": null,
        "critical": false,
        "technologyNames": [
            "ALL TECHNOLOGIES"
        ]
    },
    {
        "id": 1101010,
        "name": "Avoid NATURAL JOIN queries",
        "href": "AIP/quality-rules/1101010",
        "status": null,
        "critical": false,
        "technologyNames": [
            "ALL TECHNOLOGIES"
        ]
    },
    {
        "id": 1101012,
        "name": "Specify column names instead of column numbers in ORDER BY clauses",
        "href": "AIP/quality-rules/1101012",
        "status": null,
        "critical": false,
        "technologyNames": [
            "ALL TECHNOLOGIES"
        ]
    },
    {
        "id": 1101014,
        "name": "Avoid queries using old style join convention instead of ANSI-Standard joins (SQL)",
        "href": "AIP/quality-rules/1101014",
        "status": null,
        "critical": false,
        "technologyNames": [
            "ALL TECHNOLOGIES"
        ]
    },
    {
        "id": 1101016,
        "name": "Avoid Artifacts with too many parameters (SQL)",
        "href": "AIP/quality-rules/1101016",
        "status": null,
        "critical": false,
        "technologyNames": [
            "SQLAnalyzer"
        ]
    },
    {
        "id": 1101018,
        "name": "Avoid using the GROUP BY clause",
        "href": "AIP/quality-rules/1101018",
        "status": null,
        "critical": false,
        "technologyNames": [
            "SQLAnalyzer"
        ]
    },
    {
        "id": 1101024,
        "name": "Avoid using dynamic SQL in SQL Artifacts",
        "href": "AIP/quality-rules/1101024",
        "status": null,
        "critical": false,
        "technologyNames": [
            "SQLAnalyzer"
        ]
    },
    {
        "id": 1101028,
        "name": "Use MINUS or EXCEPT operator instead of NOT EXISTS and NOT IN subqueries",
        "href": "AIP/quality-rules/1101028",
        "status": null,
        "critical": false,
        "technologyNames": [
            "ALL TECHNOLOGIES"
        ]
    },
    {
        "id": 1101030,
        "name": "Avoid Artifacts with queries on too many Tables and/or Views",
        "href": "AIP/quality-rules/1101030",
        "status": null,
        "critical": false,
        "technologyNames": [
            "SQLAnalyzer"
        ]
    },
    {
        "id": 1101032,
        "name": "Avoid exists and not exists independent clauses (SQL)",
        "href": "AIP/quality-rules/1101032",
        "status": null,
        "critical": true,
        "technologyNames": [
            "ALL TECHNOLOGIES"
        ]
    },
    {
        "id": 1101034,
        "name": "DISTINCT should not be used in SQL SELECT statements",
        "href": "AIP/quality-rules/1101034",
        "status": null,
        "critical": false,
        "technologyNames": [
            "ALL TECHNOLOGIES"
        ]
    },
    {
        "id": 1101038,
        "name": "Replace OR conditions testing equality on the same identifier in SQL WHERE clauses by an IN test condition",
        "href": "AIP/quality-rules/1101038",
        "status": null,
        "critical": false,
        "technologyNames": [
            "ALL TECHNOLOGIES"
        ]
    },
    {
        "id": 1101040,
        "name": "Avoid empty catch blocks (SQL)",
        "href": "AIP/quality-rules/1101040",
        "status": null,
        "critical": true,
        "technologyNames": [
            "SQLAnalyzer"
        ]
    },
    {
        "id": 1101052,
        "name": "Use WHEN OTHERS in exception management (SQL)",
        "href": "AIP/quality-rules/1101052",
        "status": null,
        "critical": true,
        "technologyNames": [
            "SQLAnalyzer"
        ]
    },
    {
        "id": 1101054,
        "name": "Never use WHEN OTHER THEN NULL",
        "href": "AIP/quality-rules/1101054",
        "status": null,
        "critical": true,
        "technologyNames": [
            "SQLAnalyzer"
        ]
    },
    {
        "id": 1101056,
        "name": "Avoid large Tables - too many columns (SQL)",
        "href": "AIP/quality-rules/1101056",
        "status": null,
        "critical": false,
        "technologyNames": [
            "SQLAnalyzer"
        ]
    },
    {
        "id": 1101058,
        "name": "Do not mix ANSI and non-ANSI JOIN syntax in the same query",
        "href": "AIP/quality-rules/1101058",
        "status": null,
        "critical": false,
        "technologyNames": [
            "ALL TECHNOLOGIES"
        ]
    },
    {
        "id": 1101060,
        "name": "LIKE operator should not start with a wildcard character",
        "href": "AIP/quality-rules/1101060",
        "status": null,
        "critical": false,
        "technologyNames": [
            "ALL TECHNOLOGIES"
        ]
    },
    {
        "id": 1101064,
        "name": "Avoid cascading Triggers (SQL)",
        "href": "AIP/quality-rules/1101064",
        "status": null,
        "critical": false,
        "technologyNames": [
            "SQLAnalyzer"
        ]
    },
    {
        "id": 1101066,
        "name": "Avoid improperly written triangular joins with XXL tables",
        "href": "AIP/quality-rules/1101066",
        "status": null,
        "critical": false,
        "technologyNames": [
            "ALL TECHNOLOGIES"
        ]
    },
    {
        "id": 1101068,
        "name": "Avoid synonym with both private and public definition",
        "href": "AIP/quality-rules/1101068",
        "status": null,
        "critical": false,
        "technologyNames": [
            "SQLAnalyzer"
        ]
    },
    {
        "id": 1101070,
        "name": "Avoid explicit comparison with NULL",
        "href": "AIP/quality-rules/1101070",
        "status": null,
        "critical": false,
        "technologyNames": [
            "ALL TECHNOLOGIES"
        ]
    },
    {
        "id": 1101078,
        "name": "Prefer PRIVATE to PUBLIC synonym",
        "href": "AIP/quality-rules/1101078",
        "status": null,
        "critical": false,
        "technologyNames": [
            "SQLAnalyzer"
        ]
    },
    {
        "id": 1101082,
        "name": "Avoid looping chain of synonyms",
        "href": "AIP/quality-rules/1101082",
        "status": null,
        "critical": false,
        "technologyNames": [
            "SQLAnalyzer"
        ]
    },
    {
        "id": 1101084,
        "name": "Avoid Cursors inside a loop (SQL)",
        "href": "AIP/quality-rules/1101084",
        "status": null,
        "critical": true,
        "technologyNames": [
            "SQLAnalyzer"
        ]
    },
    {
        "id": 1101086,
        "name": "VARCHAR2 and NVARCHAR2 should be used",
        "href": "AIP/quality-rules/1101086",
        "status": null,
        "critical": false,
        "technologyNames": [
            "SQLAnalyzer"
        ]
    },
    {
        "id": 1101088,
        "name": "LONG and LONG RAW datatypes should no longer be used",
        "href": "AIP/quality-rules/1101088",
        "status": null,
        "critical": false,
        "technologyNames": [
            "SQLAnalyzer"
        ]
    }
]
